Workbook

Sheet 3 Statement Model
B2: Drivers | C2: =C49 -> 45291 | D2: =D49 -> 45657 | E2: =E49 -> 46022 | F2: =F49 -> 46387 | G2: =G49 -> 46752 | H2: =H49 -> 47118 | I2: =I49 -> 47483 | J2: =J49 -> 47848 | K2: =K49 -> 48213
B3: For Income statement
B4: CAGR for Revenue | D4: =D52/C53 -1 -> 0.0097834495 | E4: =E52/D53 -1 -> 0.02070106 | F4: =F52/E53 -1 -> 0.030513623 | G4: =AVERAGE(D4:F4) -> 0.020332711 | H4: =G4 -> 0.020332711 | I4: =H4 -> 0.020332711 | J4: =I4 -> 0.020332711 | K4: =J4 -> 0.020332711
B6: Product - COGS % Revenue | C6: =C55/C$53 -> 0.00018508588 | D6: =D55/D$53 -> 0.00036643201 | E6: =E55/E$53 -> 3.9120029e-05 | F6: =F55/F$53 -> 0.00013396146 | G6: =AVERAGE(C6:F6) -> 0.00018114984 | H6: =G6 -> 0.00018114984 | I6: =H6 -> 0.00018114984 | J6: =I6 -> 0.00018114984 | K6: =J6 -> 0.00018114984
B7: Services - COGS % Revenue | C7: =C56/C$53 -> 0.087275109 | D7: =D56/D$53 -> 0.100548 | E7: =E56/E$53 -> 0.094171116 | F7: =F56/F$53 -> 0.093214852 | G7: =AVERAGE(C7:F7) -> 0.09380227 | H7: =G7 -> 0.09380227 | I7: =H7 -> 0.09380227 | J7: =I7 -> 0.09380227 | K7: =J7 -> 0.09380227
B8: Opex % Revenue | C8: =C57/C$53 -> 0.4489685 | D8: =D57/D$53 -> 0.42669128 | E8: =E57/E$53 -> 0.41956692 | F8: =F57/F$53 -> 0.40887271 | G8: =AVERAGE(C8:F8) -> 0.42602485 | H8: =G8 -> 0.42602485 | I8: =H8 -> 0.42602485 | J8: =I8 -> 0.42602485 | K8: =J8 -> 0.42602485
B9: Effective finance cost rate | F9: =F68/AVERAGE(E99+E97,F99+F97) -> 0.10097316 | G9: =F9 -> 0.10097316 | H9: =G9 -> 0.10097316 | I9: =H9 -> 0.10097316 | J9: =I9 -> 0.10097316 | K9: =J9 -> 0.10097316
B10: Tax Rate -. Assumption | G10: 0.3 | H10: 0.3 | I10: 0.3 | J10: 0.3 | K10: 0.3
B11: Re-measurement gain / (loss) on defined benefit plans | C11: =-C74/C73 -> 0.00039247673 | D11: =-D74/D73 -> -0.0003009117 | E11: =-E74/E73 -> -0.00062812465 | F11: =-F74/F73 -> -0.00034730262 | G11: =-AVERAGE(C11:F11) -> 0.00022096556 | H11: =G11 -> 0.00022096556 | I11: =H11 -> 0.00022096556 | J11: =I11 -> 0.00022096556 | K11: =J11 -> 0.00022096556
B13: Component
B14: Interest income | C14: 247.1 | D14: 43.3 | E14: 970.3 | F14: 506
B15: Gain on mutual funds (including fair value gain/loss) | C15: 29 | D15: 23.9 | E15: 19.2 | F15: 35
B16: Profit on sale of equity instruments | C16: 0 | D16: 0 | E16: 1.3 | F16: 0
B17: Others | C17: 35.2 | D17: 46 | E17: 29.8 | F17: 0
B18: Total other income | C18: =SUM(C14:C17) -> 311.3 | D18: =SUM(D14:D17) -> 113.2 | E18: =SUM(E14:E17) -> 1020.6 | F18: =SUM(F14:F17) -> 541 | G18: =AVERAGE(C18:F18) -> 496.525
B20: For Balance Sheet
B21: Accounts Receivable % Revenue: | D21: =D85/D53 -> 0.051554165 | E21: =E85/E53 -> 0.046030468 | F21: =F85/F53 -> 0.043961687 | G21: =AVERAGE(C21:F21) -> 0.047182107 | H21: =G21 -> 0.047182107 | I21: =H21 -> 0.047182107 | J21: =I21 -> 0.047182107 | K21: =J21 -> 0.047182107
B22: Inventory & Others % COGS: | D22: =D86/SUM(D55:D56) -> 0.00027931661 | E22: =E86/SUM(E55:E56) -> 0.00026868588 | F22: =F86/SUM(F55:F56) -> 0.0050227218 | G22: =AVERAGE(C22:F22) -> 0.0018569081 | H22: =G22 -> 0.0018569081 | I22: =H22 -> 0.0018569081 | J22: =I22 -> 0.0018569081 | K22: =J22 -> 0.0018569081
B23: Other Assets % Op.Ex: | D23: =D91/D57 -> 1.3147027 | E23: =E91/E57 -> 1.4124787 | F23: =F91/F57 -> 1.3882488 | G23: =AVERAGE(C23:F23) -> 1.37181 | H23: =G23 -> 1.37181 | I23: =H23 -> 1.37181 | J23: =I23 -> 1.37181 | K23: =J23 -> 1.37181
B25: Accounts Payable % COGS: | D25: =D96/SUM(D55:D56) -> 3.2136772 | E25: =E96/SUM(E55:E56) -> 2.625403 | F25: =F96/SUM(F55:F56) -> 2.1109782 | G25: =AVERAGE(C25:F25) -> 2.6500195 | H25: =G25 -> 2.6500195 | I25: =H25 -> 2.6500195 | J25: =I25 -> 2.6500195 | K25: =J25 -> 2.6500195
B26: Lease Liabilities % Op.Ex: | D26: =D97/D57 -> 1.9916545 | E26: =E97/E57 -> 2.0256188 | F26: =F97/F57 -> 2.352045 | G26: =AVERAGE(C26:F26) -> 2.1231061 | H26: =G26 -> 2.1231061 | I26: =H26 -> 2.1231061 | J26: =I26 -> 2.1231061 | K26: =J26 -> 2.1231061
B27: Other Liabilities % Total Expenses: | D27: =D101/SUM(D55:D57) -> 1.3784859 | E27: =E101/SUM(E55:E57) -> 1.068483 | F27: =F101/SUM(F55:F57) -> 1.1427047 | G27: =AVERAGE(C27:F27) -> 1.1965579 | H27: =G27 -> 1.1965579 | I27: =H27 -> 1.1965579 | J27: =I27 -> 1.1965579 | K27: =J27 -> 1.1965579
B29: Equity
B30: As per the Fy 25-27 report that the VI company is planning to raise Equity worth of ₹45000 cr in Fy 27-29, So lets assume that it will equally for the forecasting years | G30: 0 | H30: 0 | I30: 0 | J30: 0 | K30: 0
B32: For Cashflow
B33: CapEx % Revenue | C33: =-C126/C53 -> 0.13340895 | D33: =-D126/D53 -> 0.03790927 | E33: =-E126/E53 -> 0.23786128 | F33: =-F126/F53 -> 0.24512715 | G33: =-15000/G53 -> -0.32822986 | H33: =-15000/H53 -> -0.32168905 | I33: =-15000/I53 -> -0.31527858 | J33: =I33 -> -0.31527858 | K33: =J33 -> -0.31527858
B34: Depreciation % Revenue | C34: =C118/C53 -> 0.33833698 | D34: =D118/D53 -> 0.32583087 | E34: =E118/E53 -> 0.30821291 | F34: =F118/F53 -> 0.29415705 | G34: =AVERAGE(C34:F34) -> 0.31663445 | H34: =G34 -> 0.31663445 | I34: =H34 -> 0.31663445 | J34: =I34 -> 0.31663445 | K34: =J34 -> 0.31663445
B35: Amortization % Revenue | C35: =C119/C53 -> 0.20860839 | D35: =D119/D53 -> 0.20581265 | E35: =E119/E53 -> 0.19742958 | F35: =F119/F53 -> 0.19944629 | G35: =AVERAGE(C35:F35) -> 0.20282423 | H35: =G35 -> 0.20282423 | I35: =H35 -> 0.20282423 | J35: =I35 -> 0.20282423 | K35: =J35 -> 0.20282423
B36: Pensions / Other Items: | C36: =C120/C53 -> 0.54918776 | D36: =D120/D53 -> 0.58698415 | E36: =E120/E53 -> 0.53997377 | F36: =F120/F53 -> -0.83964813 | G36: =AVERAGE(C36:F36) -> 0.20912439 | H36: =G36 -> 0.20912439 | I36: =H36 -> 0.20912439 | J36: =I36 -> 0.20912439 | K36: =J36 -> 0.20912439
B38: Acquisitions & Other: | C38: =C127 | D38: =D127 -> -292.9 | E38: =E127 -> -5911.8 | F38: =F127 -> 4875 | G38: =F38 -> 4875 | H38: =G38 -> 4875 | I38: =H38 -> 4875 | J38: =I38 -> 4875 | K38: =J38 -> 4875
B40: New funding required: | G40: =MAX(0,G42-(F84+G123+G128+G131-G68)) -> 8272.4132 | H40: =MAX(0,H42-(G84+H123+H128+H131-H68)) -> 15537.98 | I40: =MAX(0,I42-(H84+I123+I128+I131-I68)) -> 13675.077 | J40: =MAX(0,J42-(I84+J123+J128+J131-J68)) -> 14592.968 | K40: =MAX(0,K42-(J84+K123+K128+K131-K68)) -> 15931.136
B41: Common Dividends % Net Income | C41: =C132/C75 -> 0 | D41: =D132/D75 -> -3.2002253e-06 | E41: =E132/E75 -> -3.6495951e-06 | F41: =F132/F75 -> 0
B42: Minimum year-end cash: | G42: 2000 | H42: 2000 | I42: 2000 | J42: 2000 | K42: 2000
G48: FORECAST
B49: Income Statement: | C49: 45291 | D49: =EOMONTH(C49,12) -> 45657 | E49: =EOMONTH(D49,12) -> 46022 | F49: =EOMONTH(E49,12) -> 46387 | G49: =EOMONTH(F49,12) -> 46752 | H49: =EOMONTH(G49,12) -> 47118 | I49: =EOMONTH(H49,12) -> 47483 | J49: =EOMONTH(I49,12) -> 47848 | K49: =EOMONTH(J49,12) -> 48213
B51: Products: | C51: 8.7 | D51: 17.8 | E51: 2 | F51: 7
B52: Services: | C52: 42133.9 | D52: 42554.9 | E52: 43454 | F52: 44782
B53: Total Income: | C53: =SUM(C51:C52) -> 42142.6 | D53: =SUM(D51:D52) -> 42572.7 | E53: =SUM(E51:E52) -> 43456 | F53: =SUM(F51:F52) -> 44789 | G53: =F53*(1+G4) -> 45699.682 | H53: =G53*(1+H4) -> 46628.88 | I53: =H53*(1+I4) -> 47576.972 | J53: =I53*(1+J4) -> 48544.341 | K53: =J53*(1+K4) -> 49531.379
B55: Cost of Products: | C55: 7.8 | D55: 15.6 | E55: 1.7 | F55: 6 | G55: =G$53*G6 -> 8.2784902 | H55: =H$53*H6 -> 8.4468144 | I55: =I$53*I6 -> 8.618561 | J55: =J$53*J6 -> 8.7937997 | K55: =K$53*K6 -> 8.9726015
B56: Cost of Services: | C56: 3678 | D56: 4280.6 | E56: 4092.3 | F56: 4175 | G56: =G$53*G7 -> 4286.7339 | H56: =H$53*H7 -> 4373.8948 | I56: =I$53*I7 -> 4462.8279 | J56: =J$53*J7 -> 4553.5693 | K56: =K$53*K7 -> 4646.1557
B57: Operating Expenses: | C57: 18920.7 | D57: 18165.4 | E57: 18232.7 | F57: 18313 | G57: =G$53*G8 -> 19469.2 | H57: =H$53*H8 -> 19865.062 | I57: =I$53*I8 -> 20268.972 | J57: =J$53*J8 -> 20681.096 | K57: =K$53*K8 -> 21101.598
B58: Operating Income: | C58: =C53-SUM(C55:C57) -> 19536.1 | D58: =D53-SUM(D55:D57) -> 20111.1 | E58: =E53-SUM(E55:E57) -> 21129.3 | F58: =F53-SUM(F55:F57) -> 22295 | G58: =SUM(G55:G57) -> 23764.213 | H58: =SUM(H55:H57) -> 24247.404 | I58: =SUM(I55:I57) -> 24740.419 | J58: =SUM(J55:J57) -> 25243.459 | K58: =SUM(K55:K57) -> 25756.727
B60: +/- Other Income / Expense | C60: =C61+C62 -> -563.4 | D60: =D61+D62 -> 0.5 | E60: =E61+E62 -> 250.9 | F60: =F61+F62 -> 58193 | G60: =SUM(G61:G62) -> -442.275 | H60: =SUM(H61:H62) -> -442.275 | I60: =SUM(I61:I62) -> -442.275 | J60: =SUM(J61:J62) -> -442.275 | K60: =SUM(K61:K62) -> -442.275
B61: + Other Income | C61: 324 | D61: 942.2 | E61: 1138 | F61: 59232 | G61: =G18 -> 496.525 | H61: =G61 -> 496.525 | I61: =H61 -> 496.525 | J61: =I61 -> 496.525 | K61: =J61 -> 496.525
B62: - Other Expense | C62: -887.4 | D62: -941.7 | E62: -887.1 | F62: -1039 | G62: =AVERAGE(C62:F62) -> -938.8 | H62: =G62 -> -938.8 | I62: =H62 -> -938.8 | J62: =I62 -> -938.8 | K62: =J62 -> -938.8
B63: - Non-Service Pension Expense | C63: 1866.3 | D63: 2122.4 | E63: 2230.9 | F63: 2337 | G63: =F63 -> 2337 | H63: =G63 -> 2337 | I63: =H63 -> 2337 | J63: =I63 -> 2337 | K63: =J63 -> 2337
B64: - Depreciation | C64: 14258.4 | D64: 13871.5 | E64: 13393.7 | F64: 13175 | G64: =G118 -> 14470.094 | H64: =H118 -> 14764.31 | I64: =I118 -> 15064.508 | J64: =J118 -> 15370.811 | K64: =K118 -> 15683.341
B65: - Amortisation | C65: 8791.3 | D65: 8762 | E65: 8579.5 | F65: 8933 | G65: =G119 -> 9269.0027 | H65: =H119 -> 9457.4666 | I65: =I119 -> 9649.7626 | J65: =J119 -> 9845.9684 | K65: =K119 -> 10046.164
B66: +/- Interest Income / Expense | C66: =C67-C68 -> -23354.3 | D66: =D67-D68 -> -25765.5 | E66: =E67-E68 -> -24543.4 | F66: =F67-F68 -> -21495 | G66: =G67-G68 -> -19352.424 | H66: =H67-H68 -> -20069.104 | I66: =I67-I68 -> -21420.83 | J66: =J67-J68 -> -22858.823 | K66: =K67-K68 -> -24421.569
B67: + Interest Income:
B68: - Interest expense: | C68: 23354.3 | D68: 25765.5 | E68: 24543.4 | F68: 21495 | G68: =G$9*(F$99+AVERAGE(F$97,G$97)) -> 19352.424 | H68: =H$9*(G$99+AVERAGE(G$97,H$97)) -> 20069.104 | I68: =I$9*(H$99+AVERAGE(H$97,I$97)) -> 21420.83 | J68: =J$9*(I$99+AVERAGE(I$97,J$97)) -> 22858.823 | K68: =K$9*(J$99+AVERAGE(J$97,K$97)) -> 24421.569
B69: Pre-tax Income: | C69: =C58+C60-C63+C66-C64-C65 -> -29297.6 | D69: =D58+D60-D63+D66-D64-D65 -> -30409.8 | E69: =E58+E60-E63+E66-E64-E65 -> -27367.3 | F69: =F58+F60-F63+F66-F64-F65 -> 34548 | G69: =G58+G60-G63+G66-G64-G65 -> -22106.583 | H69: =H58+H60-H63+H66-H64-H65 -> -22822.752 | I69: =I58+I60-I63+I66-I64-I65 -> -24173.957 | J69: =J58+J60-J63+J66-J64-J65 -> -25611.419 | K69: =K58+K60-K63+K66-K64-K65 -> -27173.622
B71: Income taxes: | C71: 3.5 | D71: 828.6 | E71: 15.8 | F71: -4 | G71: =MAX(0,G69*G10) -> 0 | H71: =MAX(0,H69*H10) -> 0 | I71: =MAX(0,I69*I10) -> 0 | J71: =MAX(0,J69*J10) -> 0 | K71: =MAX(0,K69*K10) -> 0
B73: Net Income: | C73: =SUM(C69-C71) -> -29301.1 | D73: =SUM(D69-D71) -> -31238.4 | E73: =SUM(E69-E71) -> -27383.1 | F73: =SUM(F69-F71) -> 34552 | G73: =SUM(G69-G71) -> -22106.583 | H73: =SUM(H69-H71) -> -22822.752 | I73: =SUM(I69-I71) -> -24173.957 | J73: =SUM(J69-J71) -> -25611.419 | K73: =SUM(K69-K71) -> -27173.622
B74: (-) Re-measurement gain / (loss) on defined benefit plans | C74: 11.5 | D74: -9.4 | E74: -17.2 | F74: 12 | G74: =G73*G11 -> -4.8847934 | H74: =H73*H11 -> -5.0430422 | I74: =I73*I11 -> -5.3416119 | J74: =J73*J11 -> -5.6592414 | K74: =K73*K11 -> -6.0044345
B75: Net Income to Parent: | C75: =SUM(C73:C74) -> -29289.6 | D75: =SUM(D73:D74) -> -31247.8 | E75: =SUM(E73:E74) -> -27400.3 | F75: =SUM(F73:F74) -> 34564 | G75: =SUM(G73:G74) -> -22111.468 | H75: =SUM(H73:H74) -> -22827.795 | I75: =SUM(I73:I74) -> -24179.299 | J75: =SUM(J73:J74) -> -25617.078 | K75: =SUM(K73:K74) -> -27179.626
B81: Balance sheet | C81: =C49 -> 45291 | D81: =D49 -> 45657 | E81: =E49 -> 46022 | F81: =F49 -> 46387 | G81: =G49 -> 46752 | H81: =H49 -> 47118 | I81: =I49 -> 47483 | J81: =J49 -> 47848 | K81: =K49 -> 48213
B83: Assets:
B84: Cash & Bank | C84: ='Balance Sheet'!H25 -> 855.4 | D84: ='Balance Sheet'!I25 -> 536.2 | E84: ='Balance Sheet'!J25 -> 10568.5 | F84: ='Balance Sheet'!K25 -> 5731 | G84: =G139 -> 2000 | H84: =H139 -> 2000 | I84: =I139 -> 2000 | J84: =J139 -> 2000 | K84: =K139 -> 2000
B85: Accounts Receivable: | C85: ='Balance Sheet'!H24 -> 2164 | D85: ='Balance Sheet'!I24 -> 2194.8 | E85: ='Balance Sheet'!J24 -> 2000.3 | F85: ='Balance Sheet'!K24 -> 1969 | G85: =G21*G53 -> 2156.2073 | H85: =H21*H53 -> 2200.0488 | I85: =I21*I53 -> 2244.7817 | J85: =J21*J53 -> 2290.4242 | K85: =K21*K53 -> 2336.9948
B86: Inventory & Others: | C86: ='Balance Sheet'!H$21 -> 16.3 | D86: ='Balance Sheet'!I$21 -> 1.2 | E86: ='Balance Sheet'!J$21 -> 1.1 | F86: ='Balance Sheet'!K$21 -> 21 | G86: =G22*SUM(G55:G56) -> 7.9754433 | H86: =H22*SUM(H55:H56) -> 8.1376057 | I86: =I22*SUM(I55:I56) -> 8.3030653 | J86: =J22*SUM(J55:J56) -> 8.4718891 | K86: =K22*SUM(K55:K56) -> 8.6441456
B87: Net PP&E, Goodwill & Intangible assets: | C87: ='Balance Sheet'!H10 -> 174131.6 | D87: ='Balance Sheet'!I10 -> 158313.9 | E87: ='Balance Sheet'!J10 -> 159531.8 | F87: ='Balance Sheet'!K10 -> 158360 | G87: =F87-G126-G118-G119 -> 149620.9 | H87: =G87-H126-H118-H119 -> 140399.13 | I87: =H87-I126-I118-I119 -> 130684.86 | J87: =I87-J126-J118-J119 -> 120773.07 | K87: =J87-K126-K118-K119 -> 110659.75
B88: Investments accounted for using the equity method: | C88: ='Balance Sheet'!H14 -> 5.8 | D88: ='Balance Sheet'!I14 -> 0.5 | E88: ='Balance Sheet'!J14 -> 0 | F88: ='Balance Sheet'!K14 -> 107 | G88: =F88 -> 107 | H88: =G88 -> 107 | I88: =H88 -> 107 | J88: =I88 -> 107 | K88: =J88 -> 107
B89: Assets which are for Sale: | C89: ='Balance Sheet'!C31 -> 49.3 | D89: ='Balance Sheet'!D31 -> 49.3 | E89: ='Balance Sheet'!E31 -> 0 | F89: ='Balance Sheet'!F31 -> 0 | G89: 0 | H89: 0 | I89: 0 | J89: 0 | K89: 0
B90: Tax Assets | C90: ='Balance Sheet'!H$17 -> 13.5 | D90: ='Balance Sheet'!I$17 -> 19.7 | E90: ='Balance Sheet'!J$17 -> 11.6 | F90: ='Balance Sheet'!K$17 -> 27 | G90: =F90 -> 27 | H90: =G90 -> 27 | I90: =H90 -> 27 | J90: =I90 -> 27 | K90: =J90 -> 27
B91: Other Assets: | C91: ='Balance Sheet'!H16 -> 30006.8 | D91: ='Balance Sheet'!I16 -> 23882.1 | E91: ='Balance Sheet'!J16 -> 25753.3 | F91: ='Balance Sheet'!K16 -> 25423 | G91: =G23*G57 -> 26708.045 | H91: =H23*H57 -> 27251.091 | I91: =I23*I57 -> 27805.18 | J91: =J23*J57 -> 28370.535 | K91: =K23*K57 -> 28947.385
B92: Total Assets: | C92: =SUM(C84:C91) -> 207242.7 | D92: =SUM(D84:D91) -> 184997.7 | E92: =SUM(E84:E91) -> 197866.6 | F92: =SUM(F84:F91) -> 191638 | G92: =SUM(G84:G91) -> 180627.13 | H92: =SUM(H84:H91) -> 171992.41 | I92: =SUM(I84:I91) -> 162877.12 | J92: =SUM(J84:J91) -> 153576.5 | K92: =SUM(K84:K91) -> 144086.77
B94: Liabilities & Equity
B96: Accounts Payable: | C96: ='Balance Sheet'!H46 -> 13642.2 | D96: ='Balance Sheet'!I46 -> 13806.6 | E96: ='Balance Sheet'!J46 -> 10748.4 | F96: ='Balance Sheet'!K46 -> 8826 | G96: =G25*SUM(G55:G56) -> 11381.867 | H96: =H25*SUM(H55:H56) -> 11613.291 | I96: =I25*SUM(I55:I56) -> 11849.42 | J96: =J25*SUM(J55:J56) -> 12090.351 | K96: =K25*SUM(K55:K56) -> 12336.181
B97: Lease Liabilities: | C97: ='Balance Sheet'!H45 -> 36180 | D97: ='Balance Sheet'!I45 -> 36179.2 | E97: ='Balance Sheet'!J45 -> 36932.5 | F97: ='Balance Sheet'!K45 -> 43073 | G97: =G26*G57 -> 41335.178 | H97: =H26*H57 -> 42175.634 | I97: =I26*I57 -> 43033.179 | J97: =J26*J57 -> 43908.16 | K97: =K26*K57 -> 44800.932
B98: Provisions: | C98: ='Balance Sheet'!H48 -> 38.3 | D98: ='Balance Sheet'!I48 -> 57.4 | E98: ='Balance Sheet'!J48 -> 78.4 | F98: ='Balance Sheet'!K48 -> 71 | G98: =F98-G74 -> 75.884793 | H98: =G98-H74 -> 80.927836 | I98: =H98-I74 -> 86.269447 | J98: =I98-J74 -> 91.928689 | K98: =J98-K74 -> 97.933123
B99: Total Debt: | C99: ='Balance Sheet'!H43 -> 201586 | D99: ='Balance Sheet'!I43 -> 207629.8 | E99: ='Balance Sheet'!J43 -> 196296.2 | F99: ='Balance Sheet'!K43 -> 149455 | G99: =F99+G131+G40 -> 157001.41 | H99: =G99+H131+H40 -> 169539.39 | I99: =H99+I131+I40 -> 182914.47 | J99: =I99+J131+J40 -> 197507.44 | K99: =J99+K131+K40 -> 213438.57
B100: Tax Liabilities | C100: ='Balance Sheet'!H47 -> 0 | D100: ='Balance Sheet'!I47 -> 528.5 | E100: ='Balance Sheet'!J47 -> 275.6 | F100: ='Balance Sheet'!K47 -> 267 | G100: =F100 -> 267 | H100: =G100 -> 267 | I100: =H100 -> 267 | J100: =I100 -> 267 | K100: =J100 -> 267
B101: Other Liabilities: | C101: ='Balance Sheet'!H49 -> 30155.3 | D101: ='Balance Sheet'!I49 -> 30963 | E101: ='Balance Sheet'!J49 -> 23855.7 | F101: ='Balance Sheet'!K49 -> 25704 | G101: =G27*SUM(G55:G57) -> 28435.256 | H101: =H27*SUM(H55:H57) -> 29013.422 | I101: =I27*SUM(I55:I57) -> 29603.344 | J101: =J27*SUM(J55:J57) -> 30205.26 | K101: =K27*SUM(K55:K57) -> 30819.415
B102: Total Liabilities: | C102: =SUM(C96:C101) -> 281601.8 | D102: =SUM(D96:D101) -> 289164.5 | E102: =SUM(E96:E101) -> 268186.8 | F102: =SUM(F96:F101) -> 227396 | G102: =SUM(G96:G101) -> 238496.6 | H102: =SUM(H96:H101) -> 252689.67 | I102: =SUM(I96:I101) -> 267753.68 | J102: =SUM(J96:J101) -> 284070.14 | K102: =SUM(K96:K101) -> 301760.04
B104: Equity
B105: Equity share capital | C105: ='Balance Sheet'!C36 -> 48679.7 | D105: ='Balance Sheet'!D36 -> 50119.8 | E105: ='Balance Sheet'!E36 -> 71393 | F105: ='Balance Sheet'!F36 -> 108343 | G105: =F105 -> 108343 | H105: =G105 -> 108343 | I105: =H105 -> 108343 | J105: =I105 -> 108343 | K105: =J105 -> 108343
B106: Other equity | C106: ='Balance Sheet'!C37 -> -123038.8 | D106: ='Balance Sheet'!D37 -> -154286.6 | E106: ='Balance Sheet'!E37 -> -141713.2 | F106: ='Balance Sheet'!F37 -> -144101 | G106: =F106+G75-G132-G133 -> -166212.47 | H106: =G106+H75-H132-H133 -> -189040.26 | I106: =H106+I75-I132-I133 -> -213219.56 | J106: =I106+J75-J132-J133 -> -238836.64 | K106: =J106+K75-K132-K133 -> -266016.27
B107: Total Equtiy | C107: =SUM(C105:C106) -> -74359.1 | D107: =SUM(D105:D106) -> -104166.8 | E107: =SUM(E105:E106) -> -70320.2 | F107: =SUM(F105:F106) -> -35758 | G107: =SUM(G105:G106) -> -57869.468 | H107: =SUM(H105:H106) -> -80697.263 | I107: =SUM(I105:I106) -> -104876.56 | J107: =SUM(J105:J106) -> -130493.64 | K107: =SUM(K105:K106) -> -157673.27
B109: Total Liabilities & Equity | C109: =C107+C102 -> 207242.7 | D109: =D107+D102 -> 184997.7 | E109: =E107+E102 -> 197866.6 | F109: =F107+F102 -> 191638 | G109: =G107+G102 -> 180627.13 | H109: =H107+H102 -> 171992.41 | I109: =I107+I102 -> 162877.12 | J109: =J107+J102 -> 153576.5 | K109: =K107+K102 -> 144086.77
B111: Check | C111: =C109-C92 -> 0 | D111: =D109-D92 -> 0 | E111: =E109-E92 -> 0 | F111: =F109-F92 -> 0 | G111: =G109-G92 -> 0 | H111: =H109-H92 -> 0 | I111: =I109-I92 -> 0 | J111: =J109-J92 -> 0 | K111: =K109-K92 -> 0
B115: CashFlow Statements | C115: =C81 -> 45291 | D115: =D81 -> 45657 | E115: =E81 -> 46022 | F115: =F81 -> 46387 | G115: =G81 -> 46752 | H115: =H81 -> 47118 | I115: =I81 -> 47483 | J115: =J81 -> 47848 | K115: =K81 -> 48213
B116: Cashflow from Operations
B117: Net Income before Tax | C117: =C69 -> -29297.6 | D117: =D69 -> -30409.8 | E117: =E69 -> -27367.3 | F117: =F69 -> 34548 | G117: =G69 -> -22106.583 | H117: =H69 -> -22822.752 | I117: =I69 -> -24173.957 | J117: =J69 -> -25611.419 | K117: =K69 -> -27173.622
B118: (+/-) Depreciation | C118: ='Cash Flows'!C12 -> 14258.4 | D118: ='Cash Flows'!D12 -> 13871.5 | E118: ='Cash Flows'!E12 -> 13393.7 | F118: ='Cash Flows'!F12 -> 13175 | G118: =G34*G53 -> 14470.094 | H118: =H34*H53 -> 14764.31 | I118: =I34*I53 -> 15064.508 | J118: =J34*J53 -> 15370.811 | K118: =K34*K53 -> 15683.341
B119: (+/-) Amortization | C119: ='Cash Flows'!C13 -> 8791.3 | D119: ='Cash Flows'!D13 -> 8762 | E119: ='Cash Flows'!E13 -> 8579.5 | F119: ='Cash Flows'!F13 -> 8933 | G119: =G35*G53 -> 9269.0027 | H119: =H35*H53 -> 9457.4666 | I119: =I35*I53 -> 9649.7626 | J119: =J35*J53 -> 9845.9684 | K119: =K35*K53 -> 10046.164
B120: (+/-) Pensions / Other Items: | C120: ='Cash Flows'!H13 -> 23144.2 | D120: ='Cash Flows'!I13 -> 24989.5 | E120: ='Cash Flows'!J13 -> 23465.1 | F120: ='Cash Flows'!K13 -> -37607 | G120: =G68 -> 19352.424 | H120: =H68 -> 20069.104 | I120: =I68 -> 21420.83 | J120: =J68 -> 22858.823 | K120: =K68 -> 24421.569
B121: (+/-) Change in working capital: | C121: ='Cash Flows'!H29 -> 627.5 | D121: ='Cash Flows'!I29 -> 642.5 | E121: ='Cash Flows'!J29 -> -9255.6 | F121: ='Cash Flows'!K29 -> -47 | G121: =F85-G85+F86-G86+F91-G91+SUM(G96,G97,G101)-SUM(F96:F97,F101) -> 2090.0733 | H121: =G85-H85+G86-H86+G91-H91+SUM(H96,H97,H101)-SUM(G96:G97,G101) -> 1062.9956 | I121: =H85-I85+H86-I86+H91-I91+SUM(I96,I97,I101)-SUM(H96:H97,H101) -> 1084.6092 | J121: =I85-J85+I86-J86+I91-J91+SUM(J96,J97,J101)-SUM(I96:I97,I101) -> 1106.6622 | K121: =J85-K85+J86-K86+J91-K91+SUM(K96,K97,K101)-SUM(J96:J97,J101) -> 1129.1637
B122: (+/-) Income Tax refund | C122: ='Cash Flows'!H35 -> 1344.9 | D122: ='Cash Flows'!I35 -> 2970.4 | E122: ='Cash Flows'!J35 -> 475.5 | F122: ='Cash Flows'!K35 -> 409
B123: Cashflow from Operations: | C123: =SUM(C117:C122) -> 18868.7 | D123: =SUM(D117:D122) -> 20826.1 | E123: =SUM(E117:E122) -> 9290.9 | F123: =SUM(F117:F122) -> 19411 | G123: =SUM(G117:G122) -> 23075.011 | H123: =SUM(H117:H122) -> 22531.124 | I123: =SUM(I117:I122) -> 23045.753 | J123: =SUM(J117:J122) -> 23570.846 | K123: =SUM(K117:K122) -> 24106.615
B125: Cashflow from Investing
B126: (-)CapEx: | C126: ='Cash Flows'!H39 -> -5622.2 | D126: ='Cash Flows'!I39 -> -1613.9 | E126: ='Cash Flows'!J39 -> -10336.5 | F126: ='Cash Flows'!K39 -> -10979 | G126: =G33*G53 -> -15000 | H126: =H33*H53 -> -15000 | I126: =I33*I53 -> -15000 | J126: =J33*J53 -> -15304.991 | K126: =K33*K53 -> -15616.183
B127: (-) Acquisitions & Other: | D127: ='Cash Flows'!I40 -> -292.9 | E127: ='Cash Flows'!J40 -> -5911.8 | F127: ='Cash Flows'!K40 -> 4875 | G127: 0 | H127: 0 | I127: 0 | J127: 0 | K127: 0
B128: Cashflow from Investing: | C128: =SUM(C126:C127) -> -5622.2 | D128: =SUM(D126:D127) -> -1906.8 | E128: =SUM(E126:E127) -> -16248.3 | F128: =SUM(F126:F127) -> -6104 | G128: =SUM(G126:G127) -> -15000 | H128: =SUM(H126:H127) -> -15000 | I128: =SUM(I126:I127) -> -15000 | J128: =SUM(J126:J127) -> -15304.991 | K128: =SUM(K126:K127) -> -15616.183
B130: Cashflow from Financing
B131: (+/-) changes in Debt: | C131: ='Cash Flows'!H57 -> -15111.5 | D131: ='Cash Flows'!I57 -> -18980.4 | E131: ='Cash Flows'!J57 -> -17090.5 | F131: ='Cash Flows'!K57 -> -14727 | G131: -726 | H131: -3000 | I131: -300 | L131: <- this is mentioned in VI's Fy 25-26 Annual report, Based on that we brought this numbers
B132: (-) Common Dividends: | C132: ='Cash Flows'!H59 -> 0 | D132: ='Cash Flows'!I59 -> 0.1 | E132: ='Cash Flows'!J59 -> 0.1 | F132: ='Cash Flows'!K59 -> 0 | G132: =G41*G75 -> 0 | H132: =H41*H75 -> 0 | I132: =I41*I75 -> 0 | J132: =J41*J75 -> 0 | K132: =K41*K75 -> 0
B133: (-) Stock Repurchases: | C133: ='Cash Flows'!H58 -> 432 | D133: ='Cash Flows'!I58 -> 0 | E133: ='Cash Flows'!J58 -> 24137.1 | F133: ='Cash Flows'!K58 -> 3269
B134: (+/-) New funding less interest paid: | G134: =G40-G68 -> -11080.011 | H134: =H40-H68 -> -4531.1241 | I134: =I40-I68 -> -7745.7532 | J134: =J40-J68 -> -8265.8553 | K134: =K40-K68 -> -8490.4328
B135: Cashflow from Financing: | C135: =SUM(C131:C134) -> -14679.5 | D135: =SUM(D131:D134) -> -18980.3 | E135: =SUM(E131:E134) -> 7046.7 | F135: =SUM(F131:F134) -> -11458 | G135: =SUM(G131:G134) -> -11806.011 | H135: =SUM(H131:H134) -> -7531.1241 | I135: =SUM(I131:I134) -> -8045.7532 | J135: =SUM(J131:J134) -> -8265.8553 | K135: =SUM(K131:K134) -> -8490.4328
...

Sheet Notes
A1: Vodafone Idea Limited - Consolidated Financial Statements, FY2021-22 to FY2025-26
A2: Five financial years (each ending March 31) side by side. Every figure is typed from the company's annual reports; nothing is estimated.
A4: Sources (each year is taken from its own annual report, i.e. as originally reported)
A5: FY2025-26: Annual Report 2025-26 (reported in ₹ Crore). FY2024-25: Annual Report 2024-25. FY2023-24: Annual Report 2023-24. FY2022-23: Annual Report 2022-23. (these three in ₹ Mn).
A6: FY2021-22: the 2021-22 annual report was not provided, so this column is the comparative-year column printed in the 2022-23 annual report. It may differ slightly from the original 2021-22 report if anything was regrouped.
A8: Unit
A9: All sheets are in ₹ Crore. The 2022-23, 2023-24 and 2024-25 reports (and so FY2021-22 to FY2024-25) are printed in ₹ Mn; those figures are divided by 10 (1 Crore = 10 Mn), which is exact to one decimal. The 2025-26 report is printed in whole ₹ Crore. To get the original ₹ Mn number for the older years, multiply by 10.
A10: EPS is in ₹ per share and share counts are numbers of shares; neither is converted.
A12: Sheets
A13: Balance Sheet, Profit and Loss, Cash Flows: one column per year, all years on one page.
A14: Changes in Equity: share capital roll-forward and other-equity blocks for each year, stacked on one page (a reserve-by-reserve table cannot sit in year columns).
A15: Financing Liabilities: the disclosure table printed after the cash flow statement (changes in borrowings, deferred payment obligations, interest accrued and lease liabilities), stacked by year.
... A26: Because of the whole-crore rounding in the 2025-26 report, FY2024-25 figures here (from the 2024-25 report, divided by 10) can differ by up to about one crore from that report's comparative column.

Sheet Balance Sheet
A1: Vodafone Idea Limited
A2: CONSOLIDATED BALANCE SHEET
A3: ₹ Crore (FY2021-22 to FY2024-25 reports are in ₹ Mn and are shown here divided by 10; FY2025-26 report is in ₹ Crore)
A5: Particulars | B5: FY2021-22 As at Mar 31, 2022 | C5: FY2022-23 As at Mar 31, 2023 | D5: FY2023-24 As at Mar 31, 2024 | E5: FY2024-25 As at Mar 31, 2025 | F5: FY2025-26 As at Mar 31, 2026
A6: Source | B6: Comparative in AR 2022-23 | C6: AR 2022-23 | D6: AR 2023-24 | E6: AR 2024-25 | F6: AR 2025-26
A7: Unit in the source report | B7: ₹ Mn | C7: ₹ Mn | D7: ₹ Mn | E7: ₹ Mn | F7: ₹ Crore
A8: ASSETS
A9: Non-current assets
A10: Property, plant and equipment (including RoU Assets) | B10: 53632.7 | C10: 59821.1 | D10: 52176 | E10: 56195.6 | F10: 64240 | H10: =C10+C11+C12+C13 -> 174131.6 | I10: =D10+D11+D12+D13 -> 158313.9 | J10: =E10+E11+E12+E13 -> 159531.8 | K10: =F10+F11+F12+F13 -> 158360 | L10: <- Fixed Assets
A11: Capital work-in-progress | B11: 323.9 | C11: 300.3 | D11: 638.8 | E11: 2471.6 | F11: 1454
A12: Intangible assets | B12: 103185.9 | C12: 96434.1 | D12: 87948.8 | E12: 85124 | F12: 78846
A13: Intangible assets under development | B13: 40.4 | C13: 17576.1 | D13: 17550.3 | E13: 15740.6 | F13: 13820
A14: Investments accounted for using the equity method | B14: 5.3 | C14: 5.8 | D14: 0.3 | E14: 0 | F14: 0 | H14: =C14+C23 -> 5.8 | I14: =D14+D23 -> 0.5 | J14: =E14+E23 -> 0 | K14: =F14+F23 -> 107 | L14: <-Investments
A15: Financial assets
A16: Other non-current financial assets | B16: 8849.2 | C16: 8850.1 | D16: 7100.2 | E16: 728 | F16: 3356 | H16: =C16+C18+C29+C27 -> 30006.8 | I16: =D16+D18+D29+D27 -> 23882.1 | J16: =E16+E18+E29+E27 -> 25753.3 | K16: =F16+F18+F29+F27 -> 25423 | L16: <- Other Assets
A17: Deferred tax assets (net) | B17: 6 | C17: 13.5 | D17: 13.8 | E17: 11.6 | F17: 17 | H17: =C17+C28 -> 13.5 | I17: =D17+D28 -> 19.7 | J17: =E17+E28 -> 11.6 | K17: =F17+F28 -> 27 | L17: <- Tax assets
A18: Other non-current assets | B18: 11150.2 | C18: 10338.8 | D18: 6659.7 | E18: 6555.7 | F18: 8029
A19: Total non-current assets (A) | B19: 177193.6 | C19: 193339.8 | D19: 172087.9 | E19: 166827.1 | F19: 169762
A20: Current assets
A21: Inventories | B21: 2.3 | C21: 16.3 | D21: 1.2 | E21: 1.1 | F21: 21 | H21: =C21 -> 16.3 | I21: =D21 -> 1.2 | J21: =E21 -> 1.1 | K21: =F21 -> 21 | L21: <- Inventory
A22: Financial assets
A23: Current investments | D23: 0.2 | E23: 0 | F23: 107
A24: Trade receivables | B24: 2443.9 | C24: 2164 | D24: 2194.8 | E24: 2000.3 | F24: 1969 | H24: =C24 -> 2164 | I24: =D24 -> 2194.8 | J24: =E24 -> 2000.3 | K24: =F24 -> 1969 | L24: <-accounts receivables
A25: Cash and cash equivalents | B25: 1453.2 | C25: 228.8 | D25: 167.8 | E25: 256.8 | F25: 2106 | H25: =C25+C26 -> 855.4 | I25: =D25+D26 -> 536.2 | J25: =E25+E26 -> 10568.5 | K25: =F25+F26 -> 5731 | L25: <-Cash & Bank
A26: Bank balance other than cash and cash equivalents | B26: 2043.4 | C26: 626.6 | D26: 368.4 | E26: 10311.7 | F26: 3625
A27: Other current financial assets | B27: 75.6 | C27: 39.4 | D27: 53.4 | E27: 6926.2 | F27: 2131 | H27: =B25 -> 1453.2 | I27: =C25 -> 228.8 | J27: =D25 -> 167.8 | K27: =E25 -> 256.8 | L27: =F25 -> 2106 | M27: <- Cash Changes
A28: Current tax assets | B28: 603.1 | C28: 0 | D28: 5.9 | E28: 0 | F28: 10
A29: Other current assets | B29: 10214 | C29: 10778.5 | D29: 10068.8 | E29: 11543.4 | F29: 11907
A30: Total current assets (B) | B30: 16835.5 | C30: 13853.6 | D30: 12860.5 | E30: 31039.5 | F30: 21876
A31: Assets classified as held for sale (AHFS) (C) | B31: - | C31: 49.3 | D31: 49.3 | E31: 0 | F31: 0 | H31: =C31 -> 49.3 | I31: =D31 -> 49.3 | J31: =E31 -> 0 | K31: =F31 -> 0 | L31: <- Assets which are sale
A32: Total Assets (A+B+C) | B32: 194029.1 | C32: 207242.7 | D32: 184997.7 | E32: 197866.6 | F32: 191638
A34: EQUITY AND LIABILITIES | I34: =C32-'[1]Financial Statements'!$C$92 -> 0
A35: Equity
A36: Equity share capital | B36: 32118.8 | C36: 48679.7 | D36: 50119.8 | E36: 71393 | F36: 108343
A37: Other equity | B37: -94083.6 | C37: -123038.8 | D37: -154286.6 | E37: -141713.2 | F37: -144101
A38: Total equity (A) | B38: -61964.8 | C38: -74359.1 | D38: -104166.8 | E38: -70320.2 | F38: -35758
A39: Liabilities
A40: Non-current liabilities
A41: Financial liabilities
A42: Long term borrowings
A43: Loans from banks and others | B43: 2836.3 | C43: 935.1 | D43: 0 | F43: 3275 | H43: =C43+C44+C54+C55+C56 -> 201586 | I43: =D43+D44+D54+D55+D56 -> 207629.8 | J43: =E43+E44+E54+E55+E56 -> 196296.2 | K43: =F43+F44+F54+F55+F56 -> 149455 | L43: <- Total Debt
A44: Deferred payment obligations | B44: 173114.5 | C44: 188355 | D44: 202896.2 | E44: 182768 | F44: 142473
A45: Lease liabilities | B45: 11432.5 | C45: 25061.2 | D45: 24325 | E45: 29216.6 | F45: 36221 | H45: =C45+C57 -> 36180 | I45: =D45+D57 -> 36179.2 | J45: =E45+E57 -> 36932.5 | K45: =F45+F57 -> 43073 | L45: <- Lease liabilities
A46: Trade payables | B46: 85.2 | C46: 105.8 | D46: 75.4 | E46: 0.4 | F46: 0 | H46: =C46+C58 -> 13642.2 | I46: =D46+D58 -> 13806.6 | J46: =E46+E58 -> 10748.4 | K46: =F46+F58 -> 8826 | L46: <- Accounts Payable
A47: Other non-current financial liabilities | B47: 6846.1 | C47: 6662.3 | D47: 7293.3 | E47: 135.8 | F47: 5293 | H47: =C49+C62 -> 0 | I47: =D49+D62 -> 528.5 | J47: =E49+E62 -> 275.6 | K47: =F49+F62 -> 267 | L47: <- Tax liabilities
A48: Long term provisions | B48: 38.4 | C48: 23.5 | D48: 20.9 | E48: 5 | F48: 54 | H48: =C48+C61 -> 38.3 | I48: =D48+D61 -> 57.4 | J48: =E48+E61 -> 78.4 | K48: =F48+F61 -> 71 | L48: <- Provisions
A49: Deferred tax liabilities (net) | D49: 0.4 | E49: 16.7 | F49: 8 | H49: =C47+C50+C59+C60 -> 30155.3 | I49: =D47+D50+D59+D60 -> 30963 | J49: =E47+E50+E59+E60 -> 23855.7 | K49: =F47+F50+F59+F60 -> 25704 | L49: <-Other liabilities
A50: Other non-current liabilities | B50: 507 | C50: 436.2 | D50: 412 | E50: 430.4 | F50: 383
A51: Total non-current liabilities (B) | B51: 194860 | C51: 221579.1 | D51: 235023.2 | E51: 212572.9 | F51: 187707
A52: Current liabilities
A53: Financial liabilities
A54: Short term borrowings (shown as one line in the FY2021-22 to FY2023-24 presentation) | B54: 14966.9 | C54: 12295.9 | D54: 4733.6
A55: Short term borrowings - Loans from banks and others (split out from FY2024-25) | E55: 2326 | F55: 726
A56: Short term borrowings - Deferred payment obligations (split out from FY2024-25) | E56: 11202.2 | F56: 2981
A57: Lease liabilities | B57: 11410.9 | C57: 11118.8 | D57: 11854.2 | E57: 7715.9 | F57: 6852
A58: Trade payables | B58: 13169.9 | C58: 13536.4 | D58: 13731.2 | E58: 10748 | F58: 8826
A59: Other current financial liabilities | B59: 13960.6 | C59: 15355.7 | D59: 15143.2 | E59: 14809.3 | F59: 14431
A60: Other current liabilities | B60: 7601.8 | C60: 7701.1 | D60: 8114.5 | E60: 8480.2 | F60: 5597
A61: Short term provisions | B61: 23.8 | C61: 14.8 | D61: 36.5 | E61: 73.4 | F61: 17
A62: Current tax liability (net) | D62: 528.1 | E62: 258.9 | F62: 259
A63: Total current liabilities (C) | B63: 61133.9 | C63: 60022.7 | D63: 54141.3 | E63: 55613.9 | F63: 39689 | H63: =C63+C51 -> 281601.8 | I63: =D63+D51 -> 289164.5 | J63: =E63+E51 -> 268186.8 | K63: =F63+F51 -> 227396
A64: Total Equity and Liabilities (A+B+C) | B64: 194029.1 | C64: 207242.7 | D64: 184997.7 | E64: 197866.6 | F64: 191638
A66: Source: Vodafone Idea Limited annual reports 2022-23, 2023-24, 2024-25 and 2025-26, consolidated financial statements. Each year is taken from its own year's report (as originally reported); FY2021-22 is the comparative column in the 2022-23 report.
A67: Blank cell = the line item is not presented in that year's report (statement layouts changed over the years).
A68: -* = below one million (reports in ₹ Mn) / below one crore (FY2025-26 report), not reported under the Group's rounding convention; kept as text and counted as zero in the tie-out.
A69: Each report's own wording is combined into one line list; where a report grouped items differently, see the Notes sheet.

Sheet Profit and Loss
A1: Vodafone Idea Limited
A2: CONSOLIDATED STATEMENT OF PROFIT AND LOSS
A3: ₹ Crore (FY2021-22 to FY2024-25 reports are in ₹ Mn and are shown here divided by 10; FY2025-26 report is in ₹ Crore)
A5: Particulars | B5: FY2021-22 Year ended Mar 31, 2022 | C5: FY2022-23 Year ended Mar 31, 2023 | D5: FY2023-24 Year ended Mar 31, 2024 | E5: FY2024-25 Year ended Mar 31, 2025 | F5: FY2025-26 Year ended Mar 31, 2026
A6: Source | B6: Comparative in AR 2022-23 | C6: AR 2022-23 | D6: AR 2023-24 | E6: AR 2024-25 | F6: AR 2025-26
A7: Unit in the source report | B7: ₹ Mn | C7: ₹ Mn | D7: ₹ Mn | E7: ₹ Mn | F7: ₹ Crore
A8: INCOME
A9: Service revenue | B9: 38489.5 | C9: 42133.9 | D9: 42554.9 | E9: 43453.7 | F9: 44782
A10: Sale of trading goods | B10: 8.9 | C10: 8.7 | D10: 17.8 | E10: 2 | F10: 7
A11: Other operating income | B11: 17.1 | C11: 34.6 | D11: 79 | E11: 115.6 | F11: 84
A12: Revenue from operations | B12: 38515.5 | C12: 42177.2 | D12: 42651.7 | E12: 43571.3 | F12: 44873 | H12: =C11+C13+C30+C32 -> 324 | I12: =D11+D13+D30+D32 -> 942.2 | J12: =E11+E13+E30+E32 -> 1138 | K12: =F11+F13+F30+F32 -> 59232 | L12: <- other income
A13: Other income | B13: 129.4 | C13: 311.3 | D13: 113.2 | E13: 1020.6 | F13: 541 | H13: =C23 -> 887.4 | I13: =D23 -> 941.7 | J13: =E23 -> 887.1 | K13: =F23 -> 1039 | L13: <- other expense
A14: Total income | B14: 38644.9 | C14: 42488.5 | D14: 42764.9 | E14: 44591.9 | F14: 45414
A15: EXPENSES
A16: Cost of trading goods | B16: 7 | C16: 7.8 | D16: 15.6 | E16: 1.7 | F16: 6
A17: Employee benefit expenses | B17: 1735.1 | C17: 1866.3 | D17: 2122.4 | E17: 2230.9 | F17: 2337 | H17: =C18+C19+C20+C22 -> 18920.7 | I17: =D18+D19+D20+D22 -> 18165.4 | J17: =E18+E19+E20+E22 -> 18232.7 | K17: =F18+F19+F20+F22 -> 18313 | L17: <- operating expenses
A18: Network expenses and IT outsourcing cost | B18: 9818.2 | C18: 10078.3 | D18: 9810.4 | E18: 9439.1 | F18: 9418
A19: License fees and spectrum usage charges | B19: 4198.8 | C19: 4002.1 | D19: 3672.6 | E19: 3696.2 | F19: 3851
A20: Roaming and access charges | B20: 2915.5 | C20: 3899.1 | D20: 4117.7 | E20: 4597.4 | F20: 4501
A21: Subscriber acquisition and servicing expenditure | B21: 1971.1 | C21: 3678 | D21: 4280.6 | E21: 4092.3 | F21: 4175
A22: Advertisement, business promotion expenditure and content cost | B22: 979.1 | C22: 941.2 | D22: 564.7 | E22: 500 | F22: 543
A23: Other expenses | B23: 854.6 | C23: 887.4 | D23: 941.7 | E23: 887.1 | F23: 1039
A24: Total expenses before finance costs, depreciation and amortisation (sub-total, unlabelled in the reports) | B24: 22479.4 | C24: 25360.2 | D24: 25525.7 | E24: 25444.7 | F24: 25870
A25: Profit / (Loss) before finance costs, depreciation, amortisation, share of profit / (loss) of joint venture and associates, exceptional items and tax | B25: 16165.5 | C25: 17128.3 | D25: 17239.2 | E25: 19147.2 | F25: 19544
A26: Finance costs | B26: 20980.8 | C26: 23354.3 | D26: 25765.5 | E26: 24543.4 | F26: 21495
A27: Depreciation | B27: 14656.9 | C27: 14258.4 | D27: 13871.5 | E27: 13393.7 | F27: 13175
A28: Amortisation | B28: 8927.4 | C28: 8791.3 | D28: 8762 | E28: 8579.5 | F28: 8933
A29: Profit / (Loss) before share of profit / (loss) of joint venture and associates, exceptional items and tax | B29: -28399.6 | C29: -29275.7 | D29: -31159.8 | E29: -27369.4 | F29: -24059
... A33: Profit / (Loss) before tax | B33: -28234.1 | C33: -29297.6 | D33: -30409.8 | E33: -27367.6 | F33: 34548
A34: Tax expense:
A35: - Current tax | B35: 17.3 | C35: 11.5 | D35: 828.5 | E35: -2.7 | F35: 11
A36: - Deferred tax | B36: -6 | C36: -8 | D36: 0.1 | E36: 18.5 | F36: -15 | H36: =C35+C36 -> 3.5 | I36: =D35+D36 -> 828.6 | J36: =E35+E36 -> 15.8 | K36: =F35+F36 -> -4 | L36: <- Tax
A37: Profit / (Loss) after tax for the year | B37: -28245.4 | C37: -29301.1 | D37: -31238.4 | E37: -27383.4 | F37: 34552
A39: OTHER COMPREHENSIVE INCOME / (LOSS)
A40: Items that will not be reclassified to profit or loss:
A41: Re-measurement gain / (loss) on defined benefit plans | B41: 9 | C41: 11.5 | D41: -9.4 | E41: -17.2 | F41: 12
A42: Income tax effect | B42: -0.1 | C42: -0.4 | D42: - | E42: -* | F42: -*
A43: Other comprehensive income / (loss) for the year, net of tax | B43: 8.9 | C43: 11.1 | D43: -9.4 | E43: -17.2 | F43: 12
A44: Total comprehensive income / (loss) for the year | B44: -28236.5 | C44: -29290 | D44: -31247.8 | E44: -27400.6 | F44: 34564
A46: Earnings / (loss) per equity share of ₹ 10 each (in ₹, not converted):
A47: Basic (₹) | B47: -9.83 | C47: -8.43 | D47: -6.41 | E47: -4.01 | F47: 3.21
A48: Diluted (₹) | B48: -9.83 | C48: -8.43 | D48: -6.41 | E48: -4.01 | F48: 3.21
A50: Source: Vodafone Idea Limited annual reports 2022-23, 2023-24, 2024-25 and 2025-26, consolidated financial statements. Each year is taken from its own year's report (as originally reported); FY2021-22 is the comparative column in the 2022-23 report.
A51: Blank cell = the line item is not presented in that year's report (statement layouts changed over the years).
A52: -* = below one million (reports in ₹ Mn) / below one crore (FY2025-26 report), not reported under the Group's rounding convention; kept as text and counted as zero in the tie-out.
A53: EPS is in ₹ per share and is not divided by 10.

Sheet Cash Flows
A1: Vodafone Idea Limited
A2: CONSOLIDATED STATEMENT OF CASH FLOWS
A3: ₹ Crore (FY2021-22 to FY2024-25 reports are in ₹ Mn and are shown here divided by 10; FY2025-26 report is in ₹ Crore)
A5: Particulars | B5: FY2021-22 Year ended Mar 31, 2022 | C5: FY2022-23 Year ended Mar 31, 2023 | D5: FY2023-24 Year ended Mar 31, 2024 | E5: FY2024-25 Year ended Mar 31, 2025 | F5: FY2025-26 Year ended Mar 31, 2026
A6: Source | B6: Comparative in AR 2022-23 | C6: AR 2022-23 | D6: AR 2023-24 | E6: AR 2024-25 | F6: AR 2025-26
A7: Unit in the source report | B7: ₹ Mn | C7: ₹ Mn | D7: ₹ Mn | E7: ₹ Mn | F7: ₹ Crore
A8: OPERATING ACTIVITIES
A9: Profit / (Loss) before tax | B9: -28234.1 | C9: -29297.6 | D9: -30409.8 | E9: -27367.6 | F9: 34548
A10: Adjustments to reconcile profit / (loss) before tax to net cash flows
A11: Share of (profit) / loss of joint venture and associates, net of tax | B11: -1.2 | C11: -0.5 | D11: 5.5 | E11: -1.8 | F11: 0
A12: Depreciation of property, plant and equipment (including RoU Assets) | B12: 14656.9 | C12: 14258.4 | D12: 13871.5 | E12: 13393.7 | F12: 13175 | H12: =C12+C13 -> 23049.7 | I12: =D12+D13 -> 22633.5 | J12: =E12+E13 -> 21973.2 | K12: =F12+F13 -> 22108 | L12: <- Depreciation
A13: Amortisation of intangible assets | B13: 8927.4 | C13: 8791.3 | D13: 8762 | E13: 8579.5 | F13: 8933 | H13: =SUM(C14:C27,C11) -> 23144.2 | I13: =SUM(D14:D27,D11) -> 24989.5 | J13: =SUM(E14:E27,E11) -> 23465.1 | K13: =SUM(F14:F27,F11) -> -37607 | L13: <- pension & Other items
A14: Share-based payment expense (ESOS) | B14: -1.6 | C14: 0.2 | D14: -
A15: Gain on disposal of property, plant and equipment and intangible assets (net) | B15: -67.9 | C15: -64.2 | D15: -48.6 | E15: -77.9 | F15: -144
A16: Loss / (Gain) on leasehold land | B16: -126.6 | C16: 22.4 | D16: -
A17: Accelerated depreciation on account of network re-alignment / re-farming | B17: 13.7 | C17: -
A18: Differential entry fees impact / Gain arising out of the TDSAT ruling accepted by DoT | D18: -755.5 | E18: -
A19: Exceptional items (net) | F19: -58607
A20: Finance costs | B20: 20980.8 | C20: 23354.3 | D20: 25765.5 | E20: 24543.4 | F20: 21495
A21: Bad debts / advances written off | B21: 175.6 | C21: 117 | D21: 211.9 | E21: 152.8 | F21: 126
A22: Allowance for doubtful debts / advances | B22: 47.9 | C22: 8.6 | D22: -47.8 | E22: -49.9 | F22: 108
A23: Liabilities / provisions no longer required written back | B23: -7 | C23: -17.5 | D23: -74.3 | E23: -110.7 | F23: -44
A24: Other income (single line in the FY2021-22 and FY2022-23 presentation) | B24: -105.7 | C24: -276.1
A25: Interest income | D25: -43.3 | E25: -970.3 | F25: -506
A26: Gain on Mutual Funds (including fair value gain / (loss)) | D26: -23.9 | E26: -19.2 | F26: -35
A27: Profit on sale of Equity Instruments | E27: -1.3 | F27: -
A28: Working capital adjustments
A29: (Increase) / Decrease in trade receivables | B29: -38.3 | C29: 184.7 | D29: -170.7 | E29: 103.5 | F29: -162 | H29: =SUM(C29:C33) -> 627.5 | I29: =SUM(D29:D33) -> 642.5 | J29: =SUM(E29:E33) -> -9255.6 | K29: =SUM(F29:F33) -> -47 | L29: <- Change in working capital
A30: (Increase) / Decrease in inventories | B30: -1.7 | C30: -14 | D30: 15.1 | E30: 0.1 | F30: -20
A31: Decrease / (Increase) in other financial and non-financial assets | B31: -3005.1 | C31: 1062.6 | D31: 1117.4 | E31: -5081.8 | F31: 1847
A32: (Decrease) in trade payables | B32: -343.2 | C32: -247.7 | D32: -1012.8 | E32: -3440 | F32: -979 | I32: =C34-'[1]Financial Statements'!C123 -> -1344.9 | J32: =D34-'[1]Financial Statements'!D123 -> -2970.4 | K32: =E34-'[1]Financial Statements'!E123 -> -475.8 | L32: =F34-'[1]Financial Statements'!F123 -> -409
A33: Increase / (Decrease) in other financial and non-financial liabilities | B33: 3047.6 | C33: -358.1 | D33: 693.5 | E33: -837.4 | F33: -733
A34: Cash flows from operating activities | B34: 15917.5 | C34: 17523.8 | D34: 17855.7 | E34: 8815.1 | F34: 19002
A35: Income tax refund (including TDS) (net) | B35: 1469.5 | C35: 1344.9 | D35: 2970.4 | E35: 475.5 | F35: 409 | H35: =C35 -> 1344.9 | I35: =D35 -> 2970.4 | J35: =E35 -> 475.5 | K35: =F35 -> 409
A36: Net cash flows from operating activities | B36: 17387 | C36: 18868.7 | D36: 20826.1 | E36: 9290.6 | F36: 19411
A38: INVESTING ACTIVITIES
A39: Purchase of / Payment towards property, plant and equipment and intangible assets (including CWIP and intangible assets under development) | B39: -6008.9 | C39: -3942.2 | D39: -1613.9 | E39: -10005 | F39: -10979 | H39: =C39+C40 -> -5622.2 | I39: =D39+D40 -> -1613.9 | J39: =E39+E40 -> -10336.5 | K39: =F39+F40 -> -10979 | L39: <- Capex
A40: Payment towards Spectrum - Upfront payment | B40: -103.5 | C40: -1680 | D40: 0 | E40: -331.5 | F40: 0 | H40: =SUM(C41:C49) -> 208.6 | I40: =SUM(D41:D49) -> -292.9 | J40: =SUM(E41:E49) -> -5911.8 | K40: =SUM(F41:F49) -> 4875 | L40: <- Others
A41: Payment of Deferred Payment obligation towards Spectrum | D41: -448.3 | E41: -503.7 | F41: -589
A42: Proceeds from sale of property, plant and equipment and intangible assets | B42: 120.7 | C42: 85.7 | D42: 84 | E42: 114.7 | F42: 165
A43: Proceeds from sale of Investment property / Asset held for sale (leasehold land) | B43: 187 | C43: 0 | E43: 55 | F43: 0
A44: Proceeds from sale of stake in Firefly Networks Limited (Joint Venture) | E44: 3.4 | F44: 0
A45: Payment towards purchase of stake in associates | F45: 0
A46: Repayment of loan given to joint venture | B46: 0.8 | C46: 0
A47: Net (purchase) / sale of current investments | B47: 18 | C47: 29 | D47: 23.7 | E47: 19.4 | F47: -72
A48: Interest received | B48: 58.6 | C48: 94.1 | D48: 42.2 | E48: 452.3 | F48: 820
A49: Maturity / (Placement) of Fixed deposits with banks having original maturity of 3 to 12 months (net) | B49: -3 | C49: -0.2 | D49: 5.5 | E49: -6052.9 | F49: 4551
A50: Net cash flows (used in) investing activities | B50: -5730.3 | C50: -5413.6 | D50: -1906.8 | E50: -16248.3 | F50: -6104
A52: FINANCING ACTIVITIES
A53: Proceeds from Issue of share capital through FPO (net of share issue expenses) | E53: 17695.9 | F53: 0
A54: Proceeds from issue of share capital through preferential allotment (net of share issue expenses) | B54: 4499.7 | C54: 0 | E54: 6441.2 | F54: 0
A55: Proceeds from issue of convertible share warrants (net of share issue expenses) | B55: 0 | C55: 432 | D55: 0 | F55: 0
A56: Proceeds from Issue of shares under ESOS | D56: 0.1 | E56: 0.1 | F56: 0
A57: Payment of share issue expenses towards issue of equity share capital | F57: -2 | H57: =C60+C61+C63+C64+C65+C58+C62 -> -15111.5 | I57: =D60+D61+D63+D64+D65+D58+D62 -> -18980.4 | J57: =E60+E61+E63+E64+E65+E58+E62 -> -17090.5 | K57: =F60+F61+F63+F64+F65+F58+F62 -> -14727 | L57: <- Change in Debt
A58: Payment of interest and finance charges (1) | B58: -2799.7 | C58: -2094 | D58: -2867.8 | E58: -2090.2 | F58: -2780 | H58: =C59+C57+C55+C54+C53 -> 432 | I58: =D59+D57+D55+D54+D53 -> 0 | J58: =E59+E57+E55+E54+E53 -> 24137.1 | K58: =F59+F57+F55+F54+F53 -> 3269
A59: Proceeds from issue of Non-convertible debentures (net of issue expenses) | F59: 3271 | H59: =C56 -> 0 | I59: =D56 -> 0.1 | J59: =E56 -> 0.1 | K59: =F56 -> 0
A60: Proceeds from long term borrowings | B60: 500 | C60: 1600 | D60: 0
A61: Repayment of long term borrowings | B61: -8064.1 | C61: -5946 | D61: -5916.4 | E61: -1711.4 | F61: -1600
A62: Payment of Deferred Payment obligation relating to AGR | F62: -124
A63: Proceeds from short term borrowings | B63: 2250 | C63: 1982.4 | D63: 2000 | E63: 1000 | F63: 0
A64: Repayment of short term borrowings | B64: - | C64: -2750 | D64: -3482.4 | E64: -1000 | F64: 0
A65: Payment of lease liabilities (including interest) | B65: -6939.7 | C65: -7903.9 | D65: -8713.8 | E65: -13288.9 | F65: -10223
A66: Net cash flows (used in) / generated from financing activities | B66: -10553.8 | C66: -14679.5 | D66: -18980.3 | E66: 7046.7 | F66: -11458
A68: Net increase / (decrease) in cash and cash equivalents during the year | B68: 1102.9 | C68: -1224.4 | D68: -61 | E68: 89 | F68: 1849
A69: Cash and cash equivalents at the beginning of the year | B69: 350.3 | C69: 1453.2 | D69: 228.8 | E69: 167.8 | F69: 257
A70: Cash and cash equivalents at the end of the year | B70: 1453.2 | C70: 228.8 | D70: 167.8 | E70: 256.8 | F70: 2106
A72: Source: Vodafone Idea Limited annual reports 2022-23, 2023-24, 2024-25 and 2025-26, consolidated financial statements. Each year is taken from its own year's report (as originally reported); FY2021-22 is the comparative column in the 2022-23 report.
A73: Blank cell = the line item is not presented in that year's report (statement layouts changed over the years).
A74: -* = below one million (reports in ₹ Mn) / below one crore (FY2025-26 report), not reported under the Group's rounding convention; kept as text and counted as zero in the tie-out.
A75: (1) Includes interest payment on Deferred Payment obligation. Prepared under the indirect method (Ind AS 7).

Sheet Changes in Equity
A1: Vodafone Idea Limited
A2: CONSOLIDATED STATEMENT OF CHANGES IN EQUITY, FY2021-22 to FY2025-26
A3: ₹ Crore (reports up to FY2024-25 are in ₹ Mn and are shown divided by 10; FY2025-26 report is in ₹ Crore). Share counts are numbers of shares.
A5: A. EQUITY SHARE CAPITAL - Equity shares of ₹ 10 each issued, subscribed and fully paid
A6: Particulars | B6: Numbers | C6: Amount (₹ Crore) | D6: Source
A7: As at April 1, 2021 | B7: 28735389240 | C7: 28735.4 | D7: AR 2022-23
A8: Issue of Share capital (Preferential allotment) | B8: 3383458645 | C8: 3383.4 | D8: AR 2022-23
A9: As at March 31, 2022 | B9: 32118847885 | C9: 32118.8 | D9: AR 2022-23
A10: Issue of Share capital | B10: 16560841320 | C10: 16560.9 | D10: AR 2022-23
A11: As at March 31, 2023 | B11: 48679689205 | C11: 48679.7 | D11: AR 2022-23
A12: Issue of Share capital (conversion of OCDs) | B12: 1440000000 | C12: 1440 | D12: AR 2023-24
A13: Issue of shares under Employee Stock Option Scheme (ESOS) | B13: 131170 | C13: 0.1 | D13: AR 2023-24
A14: As at March 31, 2024 | B14: 50119820375 | C14: 50119.8 | D14: AR 2023-24
A15: Issue of share capital through Further Public Offer (FPO) | B15: 16363636363 | C15: 16363.6 | D15: AR 2024-25
A16: Issue of share capital through Conversion of OCDs | B16: 160000000 | C16: 160 | D16: AR 2024-25
A17: Issue of shares under Employee Stock Option Scheme (ESOS) | B17: 122064 | C17: 0.1 | D17: AR 2024-25
A18: Issue of share capital through preferential allotment | B18: 4749456199 | C18: 4749.5 | D18: AR 2024-25
... A21: As at March 31, 2026 | B21: 108343035001 | C21: 108343 | D21: AR 2025-26
A23: B. OTHER EQUITY (₹ Crore) - each year's block as printed in its own report
B24: Reserves and surplus
A25: Particulars | B25: Capital reserve | C25: Capital reduction reserve | D25: Debenture redemption reserve | E25: Securities premium | F25: Amalgamation adjustment deficit account | G25: General reserve | H25: Retained earnings | I25: Employee stock options reserve | J25: Convertible share warrants / Share application amount pending allotment | K25: Total
A26: FY2021-22 (AR 2022-23, ₹ Mn shown as ₹ Crore)
A27: As at April 1, 2021 | B27: -8846 | C27: 27778.7 | D27: 440.8 | E27: 108469.8 | F27: -48844.4 | G27: 156.2 | H27: -146154.6 | I27: 36.1 | J27: - | K27: -66963.4
A28: Profit / (Loss) for the year ended March 31, 2022 | B28: - | C28: - | D28: - | E28: - | F28: - | G28: - | H28: -28245.4 | I28: - | J28: - | K28: -28245.4
A29: Other comprehensive income / (loss) for the year ended March 31, 2022 | B29: - | C29: - | D29: - | E29: - | F29: - | G29: - | H29: 8.9 | I29: - | J29: - | K29: 8.9
A30: Total comprehensive income / (loss) | B30: - | C30: - | D30: - | E30: - | F30: - | G30: - | H30: -28236.5 | I30: - | J30: - | K30: -28236.5
A31: Allotment of Equity Share Capital (net of issue expense of ₹ 3 Mn) | B31: - | C31: - | D31: - | E31: 1116.3 | F31: - | G31: - | H31: - | I31: - | J31: - | K31: 1116.3
A32: Share-based payment expenses | B32: - | C32: - | D32: - | E32: - | F32: - | G32: - | H32: 31.1 | I32: -31.1 | J32: - | K32: -
A33: As at March 31, 2022 | B33: -8846 | C33: 27778.7 | D33: 440.8 | E33: 109586.1 | F33: -48844.4 | G33: 156.2 | H33: -174360 | I33: 5 | J33: - | K33: -94083.6
A34: FY2022-23 (AR 2022-23)
A35: Profit / (Loss) for the year ended March 31, 2023 | B35: - | C35: - | D35: - | E35: - | F35: - | G35: - | H35: -29301.1 | I35: - | J35: - | K35: -29301.1
A36: Other comprehensive income / (loss) for the year ended March 31, 2023 | B36: - | C36: - | D36: - | E36: - | F36: - | G36: - | H36: 11.1 | I36: - | J36: - | K36: 11.1
A37: Total comprehensive income / (loss) | B37: - | C37: - | D37: - | E37: - | F37: - | G37: - | H37: -29290 | I37: - | J37: - | K37: -29290
A38: Adjustment on account of settlement of financial liability | B38: - | C38: - | D38: - | E38: - | F38: - | G38: - | H38: 330.5 | I38: - | J38: - | K38: 330.5
A39: Issue of convertible share warrants | B39: - | C39: - | D39: - | E39: - | F39: - | G39: - | H39: - | I39: - | J39: 436.2 | K39: 436.2
A40: Conversion of convertible share warrants into equity shares (net of share issue expenses of ₹ 42 Mn) | B40: - | C40: - | D40: - | E40: 4.3 | F40: - | G40: - | H40: - | I40: - | J40: -436.2 | K40: -431.9
A41: Share-based payment expenses | B41: - | C41: - | D41: - | E41: - | F41: - | G41: - | H41: 1.2 | I41: -1.2 | J41: - | K41: -
A42: As at March 31, 2023 | B42: -8846 | C42: 27778.7 | D42: 440.8 | E42: 109590.4 | F42: -48844.4 | G42: 156.2 | H42: -203318.3 | I42: 3.8 | J42: - | K42: -123038.8
A43: FY2023-24 (AR 2023-24)
A44: Profit / (Loss) for the year ended March 31, 2024 | B44: - | C44: - | D44: - | E44: - | F44: - | G44: - | H44: -31238.4 | I44: - | J44: - | K44: -31238.4
A45: Other comprehensive income / (loss) for the year ended March 31, 2024 | B45: - | C45: - | D45: - | E45: - | F45: - | G45: - | H45: -9.4 | I45: - | J45: - | K45: -9.4
A46: Total comprehensive income / (loss) | B46: - | C46: - | D46: - | E46: - | F46: - | G46: - | H46: -31247.8 | I46: - | J46: - | K46: -31247.8
A47: Issue of shares under ESOS | B47: - | C47: - | D47: - | E47: 1.4 | F47: - | G47: - | H47: - | I47: -1.4 | J47: - | K47: -
A48: Share-based payment expenses | B48: - | C48: - | D48: - | E48: - | F48: - | G48: - | H48: 0.4 | I48: -0.4 | J48: - | K48: -
A49: Transfer of debenture redemption reserve to General Reserves | B49: - | C49: - | D49: -440.8 | E49: - | F49: - | G49: 440.8 | H49: - | I49: - | J49: - | K49: -
A50: As at March 31, 2024 | B50: -8846 | C50: 27778.7 | D50: - | E50: 109591.8 | F50: -48844.4 | G50: 597 | H50: -234565.7 | I50: 2 | J50: - | K50: -154286.6
A51: FY2024-25 (AR 2024-25)
A52: Profit / (Loss) for the year ended March 31, 2025 | B52: - | C52: - | D52: - | E52: - | F52: - | G52: - | H52: -27383.4 | I52: - | J52: - | K52: -27383.4
A53: Other comprehensive income / (loss) for the year ended March 31, 2025 | B53: - | C53: - | D53: - | E53: - | F53: - | G53: - | H53: -17.2 | I53: - | J53: - | K53: -17.2
A54: Total comprehensive income / (loss) | B54: - | C54: - | D54: - | E54: - | F54: - | G54: - | H54: -27400.6 | I54: - | J54: - | K54: -27400.6
A55: Share-based payment expenses | B55: - | C55: - | D55: - | E55: - | F55: - | G55: - | H55: 0.1 | I55: -0.1 | J55: - | K55: -
A56: Issue of share capital through FPO (net of share issue expenses of ₹ 3,041 Mn) | B56: - | C56: - | D56: - | E56: 1332.3 | F56: - | G56: - | H56: - | I56: - | J56: - | K56: 1332.3
A57: Issue of shares under ESOS | B57: - | C57: - | D57: - | E57: 1.2 | F57: - | G57: - | H57: - | I57: -1.2 | J57: - | K57: -
A58: Issue of share capital through preferential allotment (net of share issue expenses of ₹ 18 Mn) | B58: - | C58: - | D58: - | E58: 1691.7 | F58: - | G58: - | H58: - | I58: - | J58: - | K58: 1691.7
A59: Discharge of Deferred payment obligation towards spectrum by way of conversion into equity | B59: - | C59: - | D59: - | E59: - | F59: - | G59: - | H59: - | I59: - | J59: 36950 | K59: 36950
A60: As at March 31, 2025 | B60: -8846 | C60: 27778.7 | D60: - | E60: 112617 | F60: -48844.4 | G60: 597 | H60: -261966.2 | I60: 0.7 | J60: 36950 | K60: -141713.2
A61: FY2025-26 (AR 2025-26, in ₹ Crore; no Debenture redemption reserve column in this report)
A62: As at April 1, 2025 (as printed in AR 2025-26; differs from the row above only by rounding to whole crore) | B62: -8846 | C62: 27779 | E62: 112617 | F62: -48844 | G62: 597 | H62: -261967 | I62: 1 | J62: 36950 | K62: -141713
A63: Profit / (Loss) for the year ended March 31, 2026 | B63: - | C63: - | E63: - | F63: - | G63: - | H63: 34552 | I63: - | J63: - | K63: 34552
A64: Other comprehensive income / (loss) for the year ended March 31, 2026 | B64: - | C64: - | E64: - | F64: - | G64: - | H64: 12 | I64: - | J64: - | K64: 12
A65: Total comprehensive income / (loss) | B65: - | C65: - | E65: - | F65: - | G65: - | H65: 34564 | I65: - | J65: - | K65: 34564
A66: Share-based payment expenses | B66: - | C66: - | E66: - | F66: - | G66: - | H66: 1 | I66: -1 | J66: - | K66: -
A67: Issue of share capital to DoT towards conversion of spectrum dues | B67: - | C67: - | E67: - | F67: - | G67: - | H67: - | I67: - | J67: -36950 | K67: -36950
A68: Share issue expenses towards issue of equity share capital | B68: - | C68: - | E68: -2 | F68: - | G68: - | H68: - | I68: - | J68: - | K68: -2
A69: As at March 31, 2026 | B69: -8846 | C69: 27779 | E69: 112615 | F69: -48844 | G69: 597 | H69: -227402 | I69: - | J69: - | K69: -144101
A71: Source: Vodafone Idea Limited annual reports 2022-23 to 2025-26, consolidated Statement of Changes in Equity. -* = below one million (reports in ₹ Mn) / below one crore (FY2025-26 report), not reported under the Group's rounding convention; kept as text and counted as zero in the tie-out.
A72: The two FY2025-26 'April 1, 2025' and FY2024-25 'March 31, 2025' rows describe the same balance; they differ by up to a crore only because the 2025-26 report rounds to whole crore.

Sheet Financing Liabilities
A1: Vodafone Idea Limited
A2: CONSOLIDATED STATEMENT OF CASH FLOWS - Disclosure of changes in liabilities arising from financing activities (incl. non-cash transactions)
A3: ₹ Crore (reports up to FY2024-25 are in ₹ Mn and are shown divided by 10; FY2025-26 report is in ₹ Crore)
A5: Particulars | B5: Loans from banks and others including current maturities | C5: Deferred payment obligations including current maturities | D5: Changes in derivative liabilities (net) | E5: Interest accrued but not due | F5: Lease liabilities
A6: FY2021-22 (AR 2022-23, ₹ Mn shown as ₹ Crore)
A7: Balance as at April 1, 2021 | B7: 23071.5 | C7: 157238.8 | D7: 44 | E7: 6395.2 | F7: 21409.9
A8: (i) Cash flow items
A9: Net proceed / (repayment) of borrowings | B9: -5308.6 | C9: -5.5 | D9: - | E9: - | F9: -
A10: Payment of Interest and finance charges | B10: - | C10: - | D10: - | E10: -2799.7 | F10: -
A11: Payment of lease liabilities | B11: - | C11: - | D11: - | E11: - | F11: -6939.7
A12: (ii) Non-cash items
A13: Exchange difference (net) | B13: 41.8 | C13: - | D13: - | E13: -41.8 | F13: -
A14: Finance cost (charged to profit and loss) | B14: - | C14: - | D14: -33.8 | E14: 19119 | F14: 1895.6
A15: Upfront fees amortisation | B15: -2.1 | C15: - | D15: - | E15: 2.1 | F15: -
A16: Interest on asset retirement obligation | B16: - | C16: - | D16: - | E16: 0.5 | F16: -
A17: Interest related to other liabilities | B17: - | C17: - | D17: - | E17: -1162 | F17: -
A18: Accrued interest on deferred payment obligation for spectrum and others transferred to borrowing on anniversary date | B18: - | C18: 14566.5 | D18: - | E18: -14566.5 | F18: -
A19: Addition towards Spectrum acquisition | B19: - | C19: 1315.3 | D19: - | E19: 13.7 | F19: -
A20: Addition of lease liabilities | B20: - | C20: - | D20: - | E20: - | F20: 7388.9
A21: Deletion of lease liabilities | B21: - | C21: - | D21: - | E21: - | F21: -911.3
A22: As at March 31, 2022 | B22: 17802.6 | C22: 173115.1 | D22: 10.2 | E22: 6960.5 | F22: 22843.4
A23: FY2022-23 (AR 2022-23)
A24: (i) Cash flow items
A25: Net proceed / (repayment) of borrowings | B25: -5112.9 | C25: -0.7 | D25: - | E25: - | F25: -
A26: Payment of Interest and finance charges | B26: - | C26: - | D26: - | E26: -2094 | F26: -
A27: Payment of lease liabilities | B27: - | C27: - | D27: - | E27: - | F27: -7903.9
A28: (ii) Non-cash items
A29: Exchange difference (net) | B29: 43.5 | C29: - | D29: - | E29: -43.5 | F29: -
A30: Finance cost (charged to profit and loss) | B30: - | C30: - | D30: -9.1 | E30: 19746.1 | F30: 3617.3
A31: Upfront fees amortisation | B31: -4 | C31: - | D31: - | E31: 4 | F31: -
A32: Interest on asset retirement obligation | B32: - | C32: - | D32: - | E32: 0.5 | F32: -
A33: Interest related to other liabilities | B33: - | C33: - | D33: - | E33: -2286 | F33: -
A34: Accrued interest on deferred payment obligation for spectrum and others transferred to borrowing on anniversary date | B34: - | C34: 14769.3 | D34: - | E34: -14769.3 | F34: -
A35: Addition towards Spectrum acquisition | B35: - | C35: 17106.3 | D35: - | E35: 487.6 | F35: -
A36: Issue of equity shares | B36: - | C36: -16133.2 | D36: - | E36: - | F36: -
A37: Adjustment on account of settlement of financial liability | B37: - | C37: - | D37: - | E37: -330.5 | F37: -
A38: Addition of lease liabilities | B38: - | C38: - | D38: - | E38: - | F38: 18684.4
A39: Deletion of lease liabilities | B39: - | C39: - | D39: - | E39: - | F39: -1061.2
A40: As at March 31, 2023 | B40: 12729.2 | C40: 188856.8 | D40: 1.1 | E40: 7675.4 | F40: 36180
A41: FY2023-24 (AR 2023-24)
A42: (i) Cash flow items
A43: Net proceed / (repayment) of borrowings | B43: -7105.5 | C43: -293.3 | D43: - | E43: - | F43: -
A44: Payment of Interest and finance charges | B44: - | C44: - | D44: - | E44: -2867.8 | F44: -
A45: Payment of Deferred Payment obligation towards Spectrum | B45: - | C45: -448.3 | D45: - | E45: - | F45: -
A46: Payment of lease liabilities | B46: - | C46: - | D46: - | E46: - | F46: -8713.8
A47: (ii) Non-cash items
A48: Finance cost (charged to profit and loss) | B48: - | C48: - | D48: -1.1 | E48: 22134.8 | F48: 3631.8
A49: Upfront fees amortisation | B49: 12.5 | C49: - | D49: - | E49: -12.5 | F49: -
A50: Interest related to other liabilities | B50: - | C50: - | D50: - | E50: -3401.2 | F50: -
A51: Accrued interest on deferred payment obligation for spectrum and others transferred to borrowing on anniversary date | B51: - | C51: 15460.6 | D51: - | E51: -15460.6 | F51: -
A52: Reclassification of deferred payment obligation | B52: - | C52: -142.2 | D52: - | E52: -14 | F52: -
A53: Issue of shares pursuant to conversion of OCDs | B53: -1440 | C53: - | D53: - | E53: - | F53: -
A54: Addition of lease liabilities | B54: - | C54: - | D54: - | E54: - | F54: 5769.5
A55: Deletion of lease liabilities | B55: - | C55: - | D55: - | E55: - | F55: -688.3
A56: As at March 31, 2024 | B56: 4196.2 | C56: 203433.6 | D56: - | E56: 8054.1 | F56: 36179.2
A57: FY2024-25 (AR 2024-25)
A58: (i) Cash flow items
A59: Repayment of borrowings (net) | B59: -1711.4 | C59: - | D59: - | E59: - | F59: -
A60: Payment of Interest and finance charges | B60: - | C60: - | D60: - | E60: -2090.2 | F60: -
A61: Payment of Deferred Payment obligation towards Spectrum | B61: - | C61: -503.7 | D61: - | E61: - | F61: -
A62: Payment of lease liabilities | B62: - | C62: - | D62: - | E62: - | F62: -13288.9
A63: (ii) Non-cash items
A64: Finance cost (charged to consolidated statement of profit and loss) | B64: - | C64: - | D64: - | E64: 20805 | F64: 3738.4
A65: Upfront fees amortisation | B65: 1.2 | C65: - | D65: - | E65: -1.2 | F65: -
A66: Interest related to other liabilities | B66: - | C66: - | D66: - | E66: -1181.8 | F66: -
A67: Accrued interest on deferred payment obligation for spectrum and others transferred to borrowing | B67: - | C67: 24813.1 | D67: - | E67: -24813.1 | F67: -
A68: Discharge of Deferred payment obligation towards spectrum by way of conversion into equity | B68: - | C68: -36950 | D68: - | E68: - | F68: -
A69: Acquisition of spectrum through deferred payment obligation | B69: - | C69: 3177.2 | D69: - | E69: - | F69: -
A70: Accrued interest on deferred payment obligation for spectrum | B70: - | C70: - | D70: - | E70: 186.7 | F70: -
A71: Issue of share capital through Conversion of OCDs | B71: -160 | C71: - | D71: - | E71: - | F71: -
A72: Addition of lease liabilities | B72: - | C72: - | D72: - | E72: - | F72: 10916.5
A73: Deletion of lease liabilities | B73: - | C73: - | D73: - | E73: - | F73: -612.7
A74: As at March 31, 2025 | B74: 2326 | C74: 193970.2 | D74: - | E74: 959.5 | F74: 36932.5
A75: FY2025-26 (AR 2025-26, in ₹ Crore; no derivative-liabilities column in this report)
A76: As at March 31, 2025 (as printed in AR 2025-26; differs from the row above only by rounding to whole crore) | B76: 2326 | C76: 193970 | E76: 960 | F76: 36933
A77: (i) Cash flow items
A78: Proceeds from borrowings (net) | B78: 3271 | C78: - | E78: - | F78: -
A79: Repayment of borrowings | B79: -1600 | C79: - | E79: - | F79: -
A80: Payment of Deferred Payment obligation pursuant to AGR judgement | B80: - | C80: -124 | E80: - | F80: -
A81: Payment of Interest and finance charges | B81: - | C81: - | E81: -2780 | F81: -
A82: Payment of Deferred Payment obligation towards Spectrum | B82: - | C82: -589 | E82: - | F82: -
A83: Payment of lease liabilities | B83: - | C83: - | E83: - | F83: -10223
A84: (ii) Non-cash items
A85: Finance cost (charged to consolidated statement of profit and loss) | B85: - | C85: - | E85: 17206 | F85: 4289
A86: Modification gain of Deferred Payment obligation towards AGR | B86: - | C86: -55622 | E86: - | F86: -
A87: Upfront fees amortisation | B87: 4 | C87: - | E87: -4 | F87: -
A88: Interest related to other liabilities | B88: - | C88: - | E88: -654 | F88: -
A89: Accrued interest on Deferred Payment obligation for Spectrum and others transferred to borrowing | B89: - | C89: 7819 | E89: -7819 | F89: -
A90: Accrued interest on Deferred Payment obligation for Spectrum capitalised | B90: - | C90: - | E90: 377 | F90: -
A91: Addition of lease liabilities | B91: - | C91: - | E91: - | F91: 12823
A92: Deletion of lease liabilities | B92: - | C92: - | E92: - | F92: -749
A93: As at March 31, 2026 | B93: 4001 | C93: 145454 | E93: 7286 | F93: 43073
A95: Source: Vodafone Idea Limited annual reports 2022-23 to 2025-26, table printed after the consolidated Statement of Cash Flows. Prepared under the indirect method (Ind AS 7). Each year's block is taken from its own year's report.
A96: -* = below one million (reports in ₹ Mn) / below one crore (FY2025-26 report), not reported under the Group's rounding convention; kept as text and counted as zero in the tie-out.

Sheet Tie-out
A1: Vodafone Idea Limited
A2: TIE-OUT: every sub-total re-added from its line items, and cross-checked between statements
A3: Each cell is the difference (recomputed minus reported) in ₹ Crore, rounded to 1 decimal. Nil = ties. Blank = not applicable to that year.
A4: Overall status | B4: =IF(COUNTIF(G8:G65,"CHECK")=0,"All checks passed","Review flagged rows") -> All checks passed
A6: Check | B6: FY2021-22 | C6: FY2022-23 | D6: FY2023-24 | E6: FY2024-25 | F6: FY2025-26 | G6: Status
A7: Balance Sheet
A8: Total non-current assets (A) | B8: =ROUND((SUM('Balance Sheet'!B10:B18))-N('Balance Sheet'!B19),1) -> 0 | C8: =ROUND((SUM('Balance Sheet'!C10:C18))-N('Balance Sheet'!C19),1) -> 0 | D8: =ROUND((SUM('Balance Sheet'!D10:D18))-N('Balance Sheet'!D19),1) -> 0 | E8: =ROUND((SUM('Balance Sheet'!E10:E18))-N('Balance Sheet'!E19),1) -> 0 | F8: =ROUND((SUM('Balance Sheet'!F10:F18))-N('Balance Sheet'!F19),1) -> 0 | G8: =IF(AND(OR(B8="",B8=0),OR(C8="",C8=0),OR(D8="",D8=0),OR(E8="",E8=0),OR(F8="",F8=0)),"OK","CHECK") -> OK
A9: Total current assets (B) | B9: =ROUND((SUM('Balance Sheet'!B21:B29))-N('Balance Sheet'!B30),1) -> 0 | C9: =ROUND((SUM('Balance Sheet'!C21:C29))-N('Balance Sheet'!C30),1) -> 0 | D9: =ROUND((SUM('Balance Sheet'!D21:D29))-N('Balance Sheet'!D30),1) -> 0 | E9: =ROUND((SUM('Balance Sheet'!E21:E29))-N('Balance Sheet'!E30),1) -> 0 | F9: =ROUND((SUM('Balance Sheet'!F21:F29))-N('Balance Sheet'!F30),1) -> 0 | G9: =IF(AND(OR(B9="",B9=0),OR(C9="",C9=0),OR(D9="",D9=0),OR(E9="",E9=0),OR(F9="",F9=0)),"OK","CHECK") -> OK
A10: Total Assets (A+B+C) | B10: =ROUND((N('Balance Sheet'!B19)+N('Balance Sheet'!B30)+N('Balance Sheet'!B31))-N('Balance Sheet'!B32),1) -> 0 | C10: =ROUND((N('Balance Sheet'!C19)+N('Balance Sheet'!C30)+N('Balance Sheet'!C31))-N('Balance Sheet'!C32),1) -> 0 | D10: =ROUND((N('Balance Sheet'!D19)+N('Balance Sheet'!D30)+N('Balance Sheet'!D31))-N('Balance Sheet'!D32),1) -> 0 | E10: =ROUND((N('Balance Sheet'!E19)+N('Balance Sheet'!E30)+N('Balance Sheet'!E31))-N('Balance Sheet'!E32),1) -> 0 | F10: =ROUND((N('Balance Sheet'!F19)+N('Balance Sheet'!F30)+N('Balance Sheet'!F31))-N('Balance Sheet'!F32),1) -> 0 | G10: =IF(AND(OR(B10="",B10=0),OR(C10="",C10=0),OR(D10="",D10=0),OR(E10="",E10=0),OR(F10="",F10=0)),"OK","CHECK") -> OK
A11: Total equity (A) | B11: =ROUND((N('Balance Sheet'!B36)+N('Balance Sheet'!B37))-N('Balance Sheet'!B38),1) -> 0 | C11: =ROUND((N('Balance Sheet'!C36)+N('Balance Sheet'!C37))-N('Balance Sheet'!C38),1) -> 0 | D11: =ROUND((N('Balance Sheet'!D36)+N('Balance Sheet'!D37))-N('Balance Sheet'!D38),1) -> 0 | E11: =ROUND((N('Balance Sheet'!E36)+N('Balance Sheet'!E37))-N('Balance Sheet'!E38),1) -> 0 | F11: =ROUND((N('Balance Sheet'!F36)+N('Balance Sheet'!F37))-N('Balance Sheet'!F38),1) -> 0 | G11: =IF(AND(OR(B11="",B11=0),OR(C11="",C11=0),OR(D11="",D11=0),OR(E11="",E11=0),OR(F11="",F11=0)),"OK","CHECK") -> OK
A12: Total non-current liabilities (B) | B12: =ROUND((SUM('Balance Sheet'!B43:B50))-N('Balance Sheet'!B51),1) -> 0 | C12: =ROUND((SUM('Balance Sheet'!C43:C50))-N('Balance Sheet'!C51),1) -> 0 | D12: =ROUND((SUM('Balance Sheet'!D43:D50))-N('Balance Sheet'!D51),1) -> 0 | E12: =ROUND((SUM('Balance Sheet'!E43:E50))-N('Balance Sheet'!E51),1) -> 0 | F12: =ROUND((SUM('Balance Sheet'!F43:F50))-N('Balance Sheet'!F51),1) -> 0 | G12: =IF(AND(OR(B12="",B12=0),OR(C12="",C12=0),OR(D12="",D12=0),OR(E12="",E12=0),OR(F12="",F12=0)),"OK","CHECK") -> OK
A13: Total current liabilities (C) | B13: =ROUND((SUM('Balance Sheet'!B54:B62))-N('Balance Sheet'!B63),1) -> 0 | C13: =ROUND((SUM('Balance Sheet'!C54:C62))-N('Balance Sheet'!C63),1) -> 0 | D13: =ROUND((SUM('Balance Sheet'!D54:D62))-N('Balance Sheet'!D63),1) -> 0 | E13: =ROUND((SUM('Balance Sheet'!E54:E62))-N('Balance Sheet'!E63),1) -> 0 | F13: =ROUND((SUM('Balance Sheet'!F54:F62))-N('Balance Sheet'!F63),1) -> 0 | G13: =IF(AND(OR(B13="",B13=0),OR(C13="",C13=0),OR(D13="",D13=0),OR(E13="",E13=0),OR(F13="",F13=0)),"OK","CHECK") -> OK
A14: Total Equity and Liabilities (A+B+C) | B14: =ROUND((N('Balance Sheet'!B38)+N('Balance Sheet'!B51)+N('Balance Sheet'!B63))-N('Balance Sheet'!B64),1) -> 0 | C14: =ROUND((N('Balance Sheet'!C38)+N('Balance Sheet'!C51)+N('Balance Sheet'!C63))-N('Balance Sheet'!C64),1) -> 0 | D14: =ROUND((N('Balance Sheet'!D38)+N('Balance Sheet'!D51)+N('Balance Sheet'!D63))-N('Balance Sheet'!D64),1) -> 0 | E14: =ROUND((N('Balance Sheet'!E38)+N('Balance Sheet'!E51)+N('Balance Sheet'!E63))-N('Balance Sheet'!E64),1) -> 0 | F14: =ROUND((N('Balance Sheet'!F38)+N('Balance Sheet'!F51)+N('Balance Sheet'!F63))-N('Balance Sheet'!F64),1) -> 0 | G14: =IF(AND(OR(B14="",B14=0),OR(C14="",C14=0),OR(D14="",D14=0),OR(E14="",E14=0),OR(F14="",F14=0)),"OK","CHECK") -> OK
A15: Balance sheet balances: Total Assets less Total Equity and Liabilities | B15: =ROUND(N('Balance Sheet'!B32)-N('Balance Sheet'!B64),1) -> 0 | C15: =ROUND(N('Balance Sheet'!C32)-N('Balance Sheet'!C64),1) -> 0 | D15: =ROUND(N('Balance Sheet'!D32)-N('Balance Sheet'!D64),1) -> 0 | E15: =ROUND(N('Balance Sheet'!E32)-N('Balance Sheet'!E64),1) -> 0 | F15: =ROUND(N('Balance Sheet'!F32)-N('Balance Sheet'!F64),1) -> 0 | G15: =IF(AND(OR(B15="",B15=0),OR(C15="",C15=0),OR(D15="",D15=0),OR(E15="",E15=0),OR(F15="",F15=0)),"OK","CHECK") -> OK
A16: Statement of Profit and Loss
A17: Revenue from operations | B17: =ROUND((SUM('Profit and Loss'!B9:B11))-N('Profit and Loss'!B12),1) -> 0 | C17: =ROUND((SUM('Profit and Loss'!C9:C11))-N('Profit and Loss'!C12),1) -> 0 | D17: =ROUND((SUM('Profit and Loss'!D9:D11))-N('Profit and Loss'!D12),1) -> 0 | E17: =ROUND((SUM('Profit and Loss'!E9:E11))-N('Profit and Loss'!E12),1) -> 0 | F17: =ROUND((SUM('Profit and Loss'!F9:F11))-N('Profit and Loss'!F12),1) -> 0 | G17: =IF(AND(OR(B17="",B17=0),OR(C17="",C17=0),OR(D17="",D17=0),OR(E17="",E17=0),OR(F17="",F17=0)),"OK","CHECK") -> OK
A18: Total income | B18: =ROUND((N('Profit and Loss'!B12)+N('Profit and Loss'!B13))-N('Profit and Loss'!B14),1) -> 0 | C18: =ROUND((N('Profit and Loss'!C12)+N('Profit and Loss'!C13))-N('Profit and Loss'!C14),1) -> 0 | D18: =ROUND((N('Profit and Loss'!D12)+N('Profit and Loss'!D13))-N('Profit and Loss'!D14),1) -> 0 | E18: =ROUND((N('Profit and Loss'!E12)+N('Profit and Loss'!E13))-N('Profit and Loss'!E14),1) -> 0 | F18: =ROUND((N('Profit and Loss'!F12)+N('Profit and Loss'!F13))-N('Profit and Loss'!F14),1) -> 0 | G18: =IF(AND(OR(B18="",B18=0),OR(C18="",C18=0),OR(D18="",D18=0),OR(E18="",E18=0),OR(F18="",F18=0)),"OK","CHECK") -> OK
A19: Total expenses before finance costs, depreciation and amortisation | B19: =ROUND((SUM('Profit and Loss'!B16:B23))-N('Profit and Loss'!B24),1) -> 0 | C19: =ROUND((SUM('Profit and Loss'!C16:C23))-N('Profit and Loss'!C24),1) -> 0 | D19: =ROUND((SUM('Profit and Loss'!D16:D23))-N('Profit and Loss'!D24),1) -> 0 | E19: =ROUND((SUM('Profit and Loss'!E16:E23))-N('Profit and Loss'!E24),1) -> 0 | F19: =ROUND((SUM('Profit and Loss'!F16:F23))-N('Profit and Loss'!F24),1) -> 0 | G19: =IF(AND(OR(B19="",B19=0),OR(C19="",C19=0),OR(D19="",D19=0),OR(E19="",E19=0),OR(F19="",F19=0)),"OK","CHECK") -> OK
A20: Profit / (Loss) before finance costs, depreciation, amortisation, JV share, exceptional items and tax | B20: =ROUND((N('Profit and Loss'!B14)-N('Profit and Loss'!B24))-N('Profit and Loss'!B25),1) -> 0 | C20: =ROUND((N('Profit and Loss'!C14)-N('Profit and Loss'!C24))-N('Profit and Loss'!C25),1) -> 0 | D20: =ROUND((N('Profit and Loss'!D14)-N('Profit and Loss'!D24))-N('Profit and Loss'!D25),1) -> 0 | E20: =ROUND((N('Profit and Loss'!E14)-N('Profit and Loss'!E24))-N('Profit and Loss'!E25),1) -> 0 | F20: =ROUND((N('Profit and Loss'!F14)-N('Profit and Loss'!F24))-N('Profit and Loss'!F25),1) -> 0 | G20: =IF(AND(OR(B20="",B20=0),OR(C20="",C20=0),OR(D20="",D20=0),OR(E20="",E20=0),OR(F20="",F20=0)),"OK","CHECK") -> OK
A21: Profit / (Loss) before share of JV and associates, exceptional items and tax | B21: =ROUND((N('Profit and Loss'!B25)-SUM('Profit and Loss'!B26:B28))-N('Profit and Loss'!B29),1) -> 0 | C21: =ROUND((N('Profit and Loss'!C25)-SUM('Profit and Loss'!C26:C28))-N('Profit and Loss'!C29),1) -> 0 | D21: =ROUND((N('Profit and Loss'!D25)-SUM('Profit and Loss'!D26:D28))-N('Profit and Loss'!D29),1) -> 0 | E21: =ROUND((N('Profit and Loss'!E25)-SUM('Profit and Loss'!E26:E28))-N('Profit and Loss'!E29),1) -> 0 | F21: =ROUND((N('Profit and Loss'!F25)-SUM('Profit and Loss'!F26:F28))-N('Profit and Loss'!F29),1) -> 0 | G21: =IF(AND(OR(B21="",B21=0),OR(C21="",C21=0),OR(D21="",D21=0),OR(E21="",E21=0),OR(F21="",F21=0)),"OK","CHECK") -> OK
A22: Profit / (Loss) before exceptional items and tax | B22: =ROUND((N('Profit and Loss'!B29)+N('Profit and Loss'!B30))-N('Profit and Loss'!B31),1) -> 0 | C22: =ROUND((N('Profit and Loss'!C29)+N('Profit and Loss'!C30))-N('Profit and Loss'!C31),1) -> 0 | D22: =ROUND((N('Profit and Loss'!D29)+N('Profit and Loss'!D30))-N('Profit and Loss'!D31),1) -> 0 | E22: =ROUND((N('Profit and Loss'!E29)+N('Profit and Loss'!E30))-N('Profit and Loss'!E31),1) -> 0 | F22: =ROUND((N('Profit and Loss'!F29)+N('Profit and Loss'!F30))-N('Profit and Loss'!F31),1) -> 0 | G22: =IF(AND(OR(B22="",B22=0),OR(C22="",C22=0),OR(D22="",D22=0),OR(E22="",E22=0),OR(F22="",F22=0)),"OK","CHECK") -> OK
A23: Profit / (Loss) before tax | B23: =ROUND((N('Profit and Loss'!B31)+N('Profit and Loss'!B32))-N('Profit and Loss'!B33),1) -> 0 | C23: =ROUND((N('Profit and Loss'!C31)+N('Profit and Loss'!C32))-N('Profit and Loss'!C33),1) -> 0 | D23: =ROUND((N('Profit and Loss'!D31)+N('Profit and Loss'!D32))-N('Profit and Loss'!D33),1) -> 0 | E23: =ROUND((N('Profit and Loss'!E31)+N('Profit and Loss'!E32))-N('Profit and Loss'!E33),1) -> 0 | F23: =ROUND((N('Profit and Loss'!F31)+N('Profit and Loss'!F32))-N('Profit and Loss'!F33),1) -> 0 | G23: =IF(AND(OR(B23="",B23=0),OR(C23="",C23=0),OR(D23="",D23=0),OR(E23="",E23=0),OR(F23="",F23=0)),"OK","CHECK") -> OK
A24: Profit / (Loss) after tax for the year | B24: =ROUND((N('Profit and Loss'!B33)-N('Profit and Loss'!B35)-N('Profit and Loss'!B36))-N('Profit and Loss'!B37),1) -> 0 | C24: =ROUND((N('Profit and Loss'!C33)-N('Profit and Loss'!C35)-N('Profit and Loss'!C36))-N('Profit and Loss'!C37),1) -> 0 | D24: =ROUND((N('Profit and Loss'!D33)-N('Profit and Loss'!D35)-N('Profit and Loss'!D36))-N('Profit and Loss'!D37),1) -> 0 | E24: =ROUND((N('Profit and Loss'!E33)-N('Profit and Loss'!E35)-N('Profit and Loss'!E36))-N('Profit and Loss'!E37),1) -> 0 | F24: =ROUND((N('Profit and Loss'!F33)-N('Profit and Loss'!F35)-N('Profit and Loss'!F36))-N('Profit and Loss'!F37),1) -> 0 | G24: =IF(AND(OR(B24="",B24=0),OR(C24="",C24=0),OR(D24="",D24=0),OR(E24="",E24=0),OR(F24="",F24=0)),"OK","CHECK") -> OK
A25: Other comprehensive income / (loss), net of tax | B25: =ROUND((N('Profit and Loss'!B41)+N('Profit and Loss'!B42))-N('Profit and Loss'!B43),1) -> 0 | C25: =ROUND((N('Profit and Loss'!C41)+N('Profit and Loss'!C42))-N('Profit and Loss'!C43),1) -> 0 | D25: =ROUND((N('Profit and Loss'!D41)+N('Profit and Loss'!D42))-N('Profit and Loss'!D43),1) -> 0 | E25: =ROUND((N('Profit and Loss'!E41)+N('Profit and Loss'!E42))-N('Profit and Loss'!E43),1) -> 0 | F25: =ROUND((N('Profit and Loss'!F41)+N('Profit and Loss'!F42))-N('Profit and Loss'!F43),1) -> 0 | G25: =IF(AND(OR(B25="",B25=0),OR(C25="",C25=0),OR(D25="",D25=0),OR(E25="",E25=0),OR(F25="",F25=0)),"OK","CHECK") -> OK
A26: Total comprehensive income / (loss) for the year | B26: =ROUND((N('Profit and Loss'!B37)+N('Profit and Loss'!B43))-N('Profit and Loss'!B44),1) -> 0 | C26: =ROUND((N('Profit and Loss'!C37)+N('Profit and Loss'!C43))-N('Profit and Loss'!C44),1) -> 0 | D26: =ROUND((N('Profit and Loss'!D37)+N('Profit and Loss'!D43))-N('Profit and Loss'!D44),1) -> 0 | E26: =ROUND((N('Profit and Loss'!E37)+N('Profit and Loss'!E43))-N('Profit and Loss'!E44),1) -> 0 | F26: =ROUND((N('Profit and Loss'!F37)+N('Profit and Loss'!F43))-N('Profit and Loss'!F44),1) -> 0 | G26: =IF(AND(OR(B26="",B26=0),OR(C26="",C26=0),OR(D26="",D26=0),OR(E26="",E26=0),OR(F26="",F26=0)),"OK","CHECK") -> OK
A27: Statement of Cash Flows
A28: Cash flows from operating activities | B28: =ROUND((N('Cash Flows'!B9)+SUM('Cash Flows'!B11:B33))-N('Cash Flows'!B34),1) -> 0 | C28: =ROUND((N('Cash Flows'!C9)+SUM('Cash Flows'!C11:C33))-N('Cash Flows'!C34),1) -> 0 | D28: =ROUND((N('Cash Flows'!D9)+SUM('Cash Flows'!D11:D33))-N('Cash Flows'!D34),1) -> 0 | E28: =ROUND((N('Cash Flows'!E9)+SUM('Cash Flows'!E11:E33))-N('Cash Flows'!E34),1) -> 0 | F28: =ROUND((N('Cash Flows'!F9)+SUM('Cash Flows'!F11:F33))-N('Cash Flows'!F34),1) -> 0 | G28: =IF(AND(OR(B28="",B28=0),OR(C28="",C28=0),OR(D28="",D28=0),OR(E28="",E28=0),OR(F28="",F28=0)),"OK","CHECK") -> OK
A29: Net cash flows from operating activities | B29: =ROUND((N('Cash Flows'!B34)+N('Cash Flows'!B35))-N('Cash Flows'!B36),1) -> 0 | C29: =ROUND((N('Cash Flows'!C34)+N('Cash Flows'!C35))-N('Cash Flows'!C36),1) -> 0 | D29: =ROUND((N('Cash Flows'!D34)+N('Cash Flows'!D35))-N('Cash Flows'!D36),1) -> 0 | E29: =ROUND((N('Cash Flows'!E34)+N('Cash Flows'!E35))-N('Cash Flows'!E36),1) -> 0 | F29: =ROUND((N('Cash Flows'!F34)+N('Cash Flows'!F35))-N('Cash Flows'!F36),1) -> 0 | G29: =IF(AND(OR(B29="",B29=0),OR(C29="",C29=0),OR(D29="",D29=0),OR(E29="",E29=0),OR(F29="",F29=0)),"OK","CHECK") -> OK
A30: Net cash flows (used in) investing activities | B30: =ROUND((SUM('Cash Flows'!B39:B49))-N('Cash Flows'!B50),1) -> 0 | C30: =ROUND((SUM('Cash Flows'!C39:C49))-N('Cash Flows'!C50),1) -> 0 | D30: =ROUND((SUM('Cash Flows'!D39:D49))-N('Cash Flows'!D50),1) -> 0 | E30: =ROUND((SUM('Cash Flows'!E39:E49))-N('Cash Flows'!E50),1) -> 0 | F30: =ROUND((SUM('Cash Flows'!F39:F49))-N('Cash Flows'!F50),1) -> 0 | G30: =IF(AND(OR(B30="",B30=0),OR(C30="",C30=0),OR(D30="",D30=0),OR(E30="",E30=0),OR(F30="",F30=0)),"OK","CHECK") -> OK
A31: Net cash flows (used in) / generated from financing activities | B31: =ROUND((SUM('Cash Flows'!B53:B65))-N('Cash Flows'!B66),1) -> 0 | C31: =ROUND((SUM('Cash Flows'!C53:C65))-N('Cash Flows'!C66),1) -> 0 | D31: =ROUND((SUM('Cash Flows'!D53:D65))-N('Cash Flows'!D66),1) -> 0 | E31: =ROUND((SUM('Cash Flows'!E53:E65))-N('Cash Flows'!E66),1) -> 0 | F31: =ROUND((SUM('Cash Flows'!F53:F65))-N('Cash Flows'!F66),1) -> 0 | G31: =IF(AND(OR(B31="",B31=0),OR(C31="",C31=0),OR(D31="",D31=0),OR(E31="",E31=0),OR(F31="",F31=0)),"OK","CHECK") -> OK
A32: Net increase / (decrease) in cash and cash equivalents | B32: =ROUND((N('Cash Flows'!B36)+N('Cash Flows'!B50)+N('Cash Flows'!B66))-N('Cash Flows'!B68),1) -> 0 | C32: =ROUND((N('Cash Flows'!C36)+N('Cash Flows'!C50)+N('Cash Flows'!C66))-N('Cash Flows'!C68),1) -> 0 | D32: =ROUND((N('Cash Flows'!D36)+N('Cash Flows'!D50)+N('Cash Flows'!D66))-N('Cash Flows'!D68),1) -> 0 | E32: =ROUND((N('Cash Flows'!E36)+N('Cash Flows'!E50)+N('Cash Flows'!E66))-N('Cash Flows'!E68),1) -> 0 | F32: =ROUND((N('Cash Flows'!F36)+N('Cash Flows'!F50)+N('Cash Flows'!F66))-N('Cash Flows'!F68),1) -> 0 | G32: =IF(AND(OR(B32="",B32=0),OR(C32="",C32=0),OR(D32="",D32=0),OR(E32="",E32=0),OR(F32="",F32=0)),"OK","CHECK") -> OK
A33: Cash and cash equivalents at the end of the year | B33: =ROUND((N('Cash Flows'!B69)+N('Cash Flows'!B68))-N('Cash Flows'!B70),1) -> 0 | C33: =ROUND((N('Cash Flows'!C69)+N('Cash Flows'!C68))-N('Cash Flows'!C70),1) -> 0 | D33: =ROUND((N('Cash Flows'!D69)+N('Cash Flows'!D68))-N('Cash Flows'!D70),1) -> 0 | E33: =ROUND((N('Cash Flows'!E69)+N('Cash Flows'!E68))-N('Cash Flows'!E70),1) -> 0 | F33: =ROUND((N('Cash Flows'!F69)+N('Cash Flows'!F68))-N('Cash Flows'!F70),1) -> 0 | G33: =IF(AND(OR(B33="",B33=0),OR(C33="",C33=0),OR(D33="",D33=0),OR(E33="",E33=0),OR(F33="",F33=0)),"OK","CHECK") -> OK
A34: Opening cash of the year = closing cash of the previous year (FY2025-26: within half a crore, as that report rounds to whole crore) | C34: =ROUND(N('Cash Flows'!C69)-N('Cash Flows'!B70),1) -> 0 | D34: =ROUND(N('Cash Flows'!D69)-N('Cash Flows'!C70),1) -> 0 | E34: =ROUND(N('Cash Flows'!E69)-N('Cash Flows'!D70),1) -> 0 | F34: =ROUND(IF(ABS(N('Cash Flows'!F69)-N('Cash Flows'!E70))<=0.5,0,N('Cash Flows'!F69)-N('Cash Flows'!E70)),1) -> 0 | G34: =IF(AND(OR(B34="",B34=0),OR(C34="",C34=0),OR(D34="",D34=0),OR(E34="",E34=0),OR(F34="",F34=0)),"OK","CHECK") -> OK
A35: Cross-statement agreement
A36: Closing cash in Cash Flow Statement = Cash and cash equivalents on Balance Sheet | B36: =ROUND(N('Cash Flows'!B70)-N('Balance Sheet'!B25),1) -> 0 | C36: =ROUND(N('Cash Flows'!C70)-N('Balance Sheet'!C25),1) -> 0 | D36: =ROUND(N('Cash Flows'!D70)-N('Balance Sheet'!D25),1) -> 0 | E36: =ROUND(N('Cash Flows'!E70)-N('Balance Sheet'!E25),1) -> 0 | F36: =ROUND(N('Cash Flows'!F70)-N('Balance Sheet'!F25),1) -> 0 | G36: =IF(AND(OR(B36="",B36=0),OR(C36="",C36=0),OR(D36="",D36=0),OR(E36="",E36=0),OR(F36="",F36=0)),"OK","CHECK") -> OK
A37: Profit / (Loss) before tax: Cash Flow Statement = Statement of Profit and Loss | B37: =ROUND(N('Cash Flows'!B9)-N('Profit and Loss'!B33),1) -> 0 | C37: =ROUND(N('Cash Flows'!C9)-N('Profit and Loss'!C33),1) -> 0 | D37: =ROUND(N('Cash Flows'!D9)-N('Profit and Loss'!D33),1) -> 0 | E37: =ROUND(N('Cash Flows'!E9)-N('Profit and Loss'!E33),1) -> 0 | F37: =ROUND(N('Cash Flows'!F9)-N('Profit and Loss'!F33),1) -> 0 | G37: =IF(AND(OR(B37="",B37=0),OR(C37="",C37=0),OR(D37="",D37=0),OR(E37="",E37=0),OR(F37="",F37=0)),"OK","CHECK") -> OK
A38: Depreciation: Cash Flow Statement = Statement of Profit and Loss | B38: =ROUND(N('Cash Flows'!B12)-N('Profit and Loss'!B27),1) -> 0 | C38: =ROUND(N('Cash Flows'!C12)-N('Profit and Loss'!C27),1) -> 0 | D38: =ROUND(N('Cash Flows'!D12)-N('Profit and Loss'!D27),1) -> 0 | E38: =ROUND(N('Cash Flows'!E12)-N('Profit and Loss'!E27),1) -> 0 | F38: =ROUND(N('Cash Flows'!F12)-N('Profit and Loss'!F27),1) -> 0 | G38: =IF(AND(OR(B38="",B38=0),OR(C38="",C38=0),OR(D38="",D38=0),OR(E38="",E38=0),OR(F38="",F38=0)),"OK","CHECK") -> OK
A39: Amortisation: Cash Flow Statement = Statement of Profit and Loss | B39: =ROUND(N('Cash Flows'!B13)-N('Profit and Loss'!B28),1) -> 0 | C39: =ROUND(N('Cash Flows'!C13)-N('Profit and Loss'!C28),1) -> 0 | D39: =ROUND(N('Cash Flows'!D13)-N('Profit and Loss'!D28),1) -> 0 | E39: =ROUND(N('Cash Flows'!E13)-N('Profit and Loss'!E28),1) -> 0 | F39: =ROUND(N('Cash Flows'!F13)-N('Profit and Loss'!F28),1) -> 0 | G39: =IF(AND(OR(B39="",B39=0),OR(C39="",C39=0),OR(D39="",D39=0),OR(E39="",E39=0),OR(F39="",F39=0)),"OK","CHECK") -> OK
A40: Finance costs: Cash Flow Statement = Statement of Profit and Loss | B40: =ROUND(N('Cash Flows'!B20)-N('Profit and Loss'!B26),1) -> 0 | C40: =ROUND(N('Cash Flows'!C20)-N('Profit and Loss'!C26),1) -> 0 | D40: =ROUND(N('Cash Flows'!D20)-N('Profit and Loss'!D26),1) -> 0 | E40: =ROUND(N('Cash Flows'!E20)-N('Profit and Loss'!E26),1) -> 0 | F40: =ROUND(N('Cash Flows'!F20)-N('Profit and Loss'!F26),1) -> 0 | G40: =IF(AND(OR(B40="",B40=0),OR(C40="",C40=0),OR(D40="",D40=0),OR(E40="",E40=0),OR(F40="",F40=0)),"OK","CHECK") -> OK
A41: Total comprehensive income: Changes in Equity = Statement of Profit and Loss | B41: =ROUND(N('Changes in Equity'!K30)-N('Profit and Loss'!B44),1) -> 0 | C41: =ROUND(N('Changes in Equity'!K37)-N('Profit and Loss'!C44),1) -> 0 | D41: =ROUND(N('Changes in Equity'!K46)-N('Profit and Loss'!D44),1) -> 0 | E41: =ROUND(N('Changes in Equity'!K54)-N('Profit and Loss'!E44),1) -> 0 | F41: =ROUND(N('Changes in Equity'!K65)-N('Profit and Loss'!F44),1) -> 0 | G41: =IF(AND(OR(B41="",B41=0),OR(C41="",C41=0),OR(D41="",D41=0),OR(E41="",E41=0),OR(F41="",F41=0)),"OK","CHECK") -> OK
A42: Equity share capital: Changes in Equity = Balance Sheet | B42: =ROUND(N('Changes in Equity'!C9)-N('Balance Sheet'!B36),1) -> 0 | C42: =ROUND(N('Changes in Equity'!C11)-N('Balance Sheet'!C36),1) -> 0 | D42: =ROUND(N('Changes in Equity'!C14)-N('Balance Sheet'!D36),1) -> 0 | E42: =ROUND(N('Changes in Equity'!C19)-N('Balance Sheet'!E36),1) -> 0 | F42: =ROUND(N('Changes in Equity'!C21)-N('Balance Sheet'!F36),1) -> 0 | G42: =IF(AND(OR(B42="",B42=0),OR(C42="",C42=0),OR(D42="",D42=0),OR(E42="",E42=0),OR(F42="",F42=0)),"OK","CHECK") -> OK
A43: Other equity (closing): Changes in Equity = Balance Sheet | B43: =ROUND(N('Changes in Equity'!K33)-N('Balance Sheet'!B37),1) -> 0 | C43: =ROUND(N('Changes in Equity'!K42)-N('Balance Sheet'!C37),1) -> 0 | D43: =ROUND(N('Changes in Equity'!K50)-N('Balance Sheet'!D37),1) -> 0 | E43: =ROUND(N('Changes in Equity'!K60)-N('Balance Sheet'!E37),1) -> 0 | F43: =ROUND(N('Changes in Equity'!K69)-N('Balance Sheet'!F37),1) -> 0 | G43: =IF(AND(OR(B43="",B43=0),OR(C43="",C43=0),OR(D43="",D43=0),OR(E43="",E43=0),OR(F43="",F43=0)),"OK","CHECK") -> OK
A44: Borrowings (loans + deferred payment obligations, incl. current maturities): Financing table = Balance Sheet | B44: =ROUND(N('Financing Liabilities'!B22)+N('Financing Liabilities'!C22)-(N('Balance Sheet'!B43)+N('Balance Sheet'!B44)+N('Balance Sheet'!B54)+N('Balance Sheet'!B55)+N('Balance Sheet'!B56)),1) -> 0 | C44: =ROUND(N('Financing Liabilities'!B40)+N('Financing Liabilities'!C40)-(N('Balance Sheet'!C43)+N('Balance Sheet'!C44)+N('Balance Sheet'!C54)+N('Balance Sheet'!C55)+N('Balance Sheet'!C56)),1) -> 0 | D44: =ROUND(N('Financing Liabilities'!B56)+N('Financing Liabilities'!C56)-(N('Balance Sheet'!D43)+N('Balance Sheet'!D44)+N('Balance Sheet'!D54)+N('Balance Sheet'!D55)+N('Balance Sheet'!D56)),1) -> 0 | E44: =ROUND(N('Financing Liabilities'!B74)+N('Financing Liabilities'!C74)-(N('Balance Sheet'!E43)+N('Balance Sheet'!E44)+N('Balance Sheet'!E54)+N('Balance Sheet'!E55)+N('Balance Sheet'!E56)),1) -> 0 | F44: =ROUND(N('Financing Liabilities'!B93)+N('Financing Liabilities'!C93)-(N('Balance Sheet'!F43)+N('Balance Sheet'!F44)+N('Balance Sheet'!F54)+N('Balance Sheet'!F55)+N('Balance Sheet'!F56)),1) -> 0 | G44: =IF(AND(OR(B44="",B44=0),OR(C44="",C44=0),OR(D44="",D44=0),OR(E44="",E44=0),OR(F44="",F44=0)),"OK","CHECK") -> OK
A45: Lease liabilities: Financing table = Balance Sheet (non-current + current) | B45: =ROUND(N('Financing Liabilities'!F22)-(N('Balance Sheet'!B45)+N('Balance Sheet'!B57)),1) -> 0 | C45: =ROUND(N('Financing Liabilities'!F40)-(N('Balance Sheet'!C45)+N('Balance Sheet'!C57)),1) -> 0 | D45: =ROUND(N('Financing Liabilities'!F56)-(N('Balance Sheet'!D45)+N('Balance Sheet'!D57)),1) -> 0 | E45: =ROUND(N('Financing Liabilities'!F74)-(N('Balance Sheet'!E45)+N('Balance Sheet'!E57)),1) -> 0 | F45: =ROUND(N('Financing Liabilities'!F93)-(N('Balance Sheet'!F45)+N('Balance Sheet'!F57)),1) -> 0 | G45: =IF(AND(OR(B45="",B45=0),OR(C45="",C45=0),OR(D45="",D45=0),OR(E45="",E45=0),OR(F45="",F45=0)),"OK","CHECK") -> OK
A46: Statement of Changes in Equity - roll-forwards
A47: Equity share capital - Number of shares: opening + issues = closing | B47: =ROUND(N('Changes in Equity'!B7)+N('Changes in Equity'!B8)-N('Changes in Equity'!B9),1) -> 0 | C47: =ROUND(N('Changes in Equity'!B9)+N('Changes in Equity'!B10)-N('Changes in Equity'!B11),1) -> 0 | D47: =ROUND(N('Changes in Equity'!B11)+N('Changes in Equity'!B12)+N('Changes in Equity'!B13)-N('Changes in Equity'!B14),1) -> 0 | E47: =ROUND(N('Changes in Equity'!B14)+N('Changes in Equity'!B15)+N('Changes in Equity'!B16)+N('Changes in Equity'!B17)+N('Changes in Equity'!B18)-N('Changes in Equity'!B19),1) -> 0 | F47: =ROUND(N('Changes in Equity'!B19)+N('Changes in Equity'!B20)-N('Changes in Equity'!B21),1) -> 0 | G47: =IF(AND(OR(B47="",B47=0),OR(C47="",C47=0),OR(D47="",D47=0),OR(E47="",E47=0),OR(F47="",F47=0)),"OK","CHECK") -> OK
A48: Equity share capital - Amount (₹ Crore): opening + issues = closing | B48: =ROUND(N('Changes in Equity'!C7)+N('Changes in Equity'!C8)-N('Changes in Equity'!C9),1) -> 0 | C48: =ROUND(N('Changes in Equity'!C9)+N('Changes in Equity'!C10)-N('Changes in Equity'!C11),1) -> 0 | D48: =ROUND(N('Changes in Equity'!C11)+N('Changes in Equity'!C12)+N('Changes in Equity'!C13)-N('Changes in Equity'!C14),1) -> 0 | E48: =ROUND(N('Changes in Equity'!C14)+N('Changes in Equity'!C15)+N('Changes in Equity'!C16)+N('Changes in Equity'!C17)+N('Changes in Equity'!C18)-N('Changes in Equity'!C19),1) -> 0 | F48: =ROUND(N('Changes in Equity'!C19)+N('Changes in Equity'!C20)-N('Changes in Equity'!C21),1) -> 0 | G48: =IF(AND(OR(B48="",B48=0),OR(C48="",C48=0),OR(D48="",D48=0),OR(E48="",E48=0),OR(F48="",F48=0)),"OK","CHECK") -> OK
A49: Other equity - Capital reserve: opening + movements = closing | B49: =ROUND(N('Changes in Equity'!B27)+N('Changes in Equity'!B28)+N('Changes in Equity'!B29)+N('Changes in Equity'!B31)+N('Changes in Equity'!B32)-N('Changes in Equity'!B33),1) -> 0 | C49: =ROUND(N('Changes in Equity'!B33)+N('Changes in Equity'!B35)+N('Changes in Equity'!B36)+N('Changes in Equity'!B38)+N('Changes in Equity'!B39)+N('Changes in Equity'!B40)+N('Changes in Equity'!B41)-N('Changes in Equity'!B42),1) -> 0 | D49: =ROUND(N('Changes in Equity'!B42)+N('Changes in Equity'!B44)+N('Changes in Equity'!B45)+N('Changes in Equity'!B47)+N('Changes in Equity'!B48)+N('Changes in Equity'!B49)-N('Changes in Equity'!B50),1) -> 0 | E49: =ROUND(N('Changes in Equity'!B50)+N('Changes in Equity'!B52)+N('Changes in Equity'!B53)+N('Changes in Equity'!B55)+N('Changes in Equity'!B56)+N('Changes in Equity'!B57)+N('Changes in Equity'!B58)+N('Changes in Equity'!B59)-N('Changes in Equity'!B60),1) -> 0 | F49: =ROUND(N('Changes in Equity'!B62)+N('Changes in Equity'!B63)+N('Changes in Equity'!B64)+N('Changes in Equity'!B66)+N('Changes in Equity'!B67)+N('Changes in Equity'!B68)-N('Changes in Equity'!B69),1) -> 0 | G49: =IF(AND(OR(B49="",B49=0),OR(C49="",C49=0),OR(D49="",D49=0),OR(E49="",E49=0),OR(F49="",F49=0)),"OK","CHECK") -> OK
A50: Other equity - Capital reduction reserve: opening + movements = closing | B50: =ROUND(N('Changes in Equity'!C27)+N('Changes in Equity'!C28)+N('Changes in Equity'!C29)+N('Changes in Equity'!C31)+N('Changes in Equity'!C32)-N('Changes in Equity'!C33),1) -> 0 | C50: =ROUND(N('Changes in Equity'!C33)+N('Changes in Equity'!C35)+N('Changes in Equity'!C36)+N('Changes in Equity'!C38)+N('Changes in Equity'!C39)+N('Changes in Equity'!C40)+N('Changes in Equity'!C41)-N('Changes in Equity'!C42),1) -> 0 | D50: =ROUND(N('Changes in Equity'!C42)+N('Changes in Equity'!C44)+N('Changes in Equity'!C45)+N('Changes in Equity'!C47)+N('Changes in Equity'!C48)+N('Changes in Equity'!C49)-N('Changes in Equity'!C50),1) -> 0 | E50: =ROUND(N('Changes in Equity'!C50)+N('Changes in Equity'!C52)+N('Changes in Equity'!C53)+N('Changes in Equity'!C55)+N('Changes in Equity'!C56)+N('Changes in Equity'!C57)+N('Changes in Equity'!C58)+N('Changes in Equity'!C59)-N('Changes in Equity'!C60),1) -> 0 | F50: =ROUND(N('Changes in Equity'!C62)+N('Changes in Equity'!C63)+N('Changes in Equity'!C64)+N('Changes in Equity'!C66)+N('Changes in Equity'!C67)+N('Changes in Equity'!C68)-N('Changes in Equity'!C69),1) -> 0 | G50: =IF(AND(OR(B50="",B50=0),OR(C50="",C50=0),OR(D50="",D50=0),OR(E50="",E50=0),OR(F50="",F50=0)),"OK","CHECK") -> OK
A51: Other equity - Debenture redemption reserve: opening + movements = closing | B51: =ROUND(N('Changes in Equity'!D27)+N('Changes in Equity'!D28)+N('Changes in Equity'!D29)+N('Changes in Equity'!D31)+N('Changes in Equity'!D32)-N('Changes in Equity'!D33),1) -> 0 | C51: =ROUND(N('Changes in Equity'!D33)+N('Changes in Equity'!D35)+N('Changes in Equity'!D36)+N('Changes in Equity'!D38)+N('Changes in Equity'!D39)+N('Changes in Equity'!D40)+N('Changes in Equity'!D41)-N('Changes in Equity'!D42),1) -> 0 | D51: =ROUND(N('Changes in Equity'!D42)+N('Changes in Equity'!D44)+N('Changes in Equity'!D45)+N('Changes in Equity'!D47)+N('Changes in Equity'!D48)+N('Changes in Equity'!D49)-N('Changes in Equity'!D50),1) -> 0 | E51: =ROUND(N('Changes in Equity'!D50)+N('Changes in Equity'!D52)+N('Changes in Equity'!D53)+N('Changes in Equity'!D55)+N('Changes in Equity'!D56)+N('Changes in Equity'!D57)+N('Changes in Equity'!D58)+N('Changes in Equity'!D59)-N('Changes in Equity'!D60),1) -> 0 | F51: =ROUND(N('Changes in Equity'!D62)+N('Changes in Equity'!D63)+N('Changes in Equity'!D64)+N('Changes in Equity'!D66)+N('Changes in Equity'!D67)+N('Changes in Equity'!D68)-N('Changes in Equity'!D69),1) -> 0 | G51: =IF(AND(OR(B51="",B51=0),OR(C51="",C51=0),OR(D51="",D51=0),OR(E51="",E51=0),OR(F51="",F51=0)),"OK","CHECK") -> OK
A52: Other equity - Securities premium: opening + movements = closing | B52: =ROUND(N('Changes in Equity'!E27)+N('Changes in Equity'!E28)+N('Changes in Equity'!E29)+N('Changes in Equity'!E31)+N('Changes in Equity'!E32)-N('Changes in Equity'!E33),1) -> 0 | C52: =ROUND(N('Changes in Equity'!E33)+N('Changes in Equity'!E35)+N('Changes in Equity'!E36)+N('Changes in Equity'!E38)+N('Changes in Equity'!E39)+N('Changes in Equity'!E40)+N('Changes in Equity'!E41)-N('Changes in Equity'!E42),1) -> 0 | D52: =ROUND(N('Changes in Equity'!E42)+N('Changes in Equity'!E44)+N('Changes in Equity'!E45)+N('Changes in Equity'!E47)+N('Changes in Equity'!E48)+N('Changes in Equity'!E49)-N('Changes in Equity'!E50),1) -> 0 | E52: =ROUND(N('Changes in Equity'!E50)+N('Changes in Equity'!E52)+N('Changes in Equity'!E53)+N('Changes in Equity'!E55)+N('Changes in Equity'!E56)+N('Changes in Equity'!E57)+N('Changes in Equity'!E58)+N('Changes in Equity'!E59)-N('Changes in Equity'!E60),1) -> 0 | F52: =ROUND(N('Changes in Equity'!E62)+N('Changes in Equity'!E63)+N('Changes in Equity'!E64)+N('Changes in Equity'!E66)+N('Changes in Equity'!E67)+N('Changes in Equity'!E68)-N('Changes in Equity'!E69),1) -> 0 | G52: =IF(AND(OR(B52="",B52=0),OR(C52="",C52=0),OR(D52="",D52=0),OR(E52="",E52=0),OR(F52="",F52=0)),"OK","CHECK") -> OK
A53: Other equity - Amalgamation adjustment deficit account: opening + movements = closing | B53: =ROUND(N('Changes in Equity'!F27)+N('Changes in Equity'!F28)+N('Changes in Equity'!F29)+N('Changes in Equity'!F31)+N('Changes in Equity'!F32)-N('Changes in Equity'!F33),1) -> 0 | C53: =ROUND(N('Changes in Equity'!F33)+N('Changes in Equity'!F35)+N('Changes in Equity'!F36)+N('Changes in Equity'!F38)+N('Changes in Equity'!F39)+N('Changes in Equity'!F40)+N('Changes in Equity'!F41)-N('Changes in Equity'!F42),1) -> 0 | D53: =ROUND(N('Changes in Equity'!F42)+N('Changes in Equity'!F44)+N('Changes in Equity'!F45)+N('Changes in Equity'!F47)+N('Changes in Equity'!F48)+N('Changes in Equity'!F49)-N('Changes in Equity'!F50),1) -> 0 | E53: =ROUND(N('Changes in Equity'!F50)+N('Changes in Equity'!F52)+N('Changes in Equity'!F53)+N('Changes in Equity'!F55)+N('Changes in Equity'!F56)+N('Changes in Equity'!F57)+N('Changes in Equity'!F58)+N('Changes in Equity'!F59)-N('Changes in Equity'!F60),1) -> 0 | F53: =ROUND(N('Changes in Equity'!F62)+N('Changes in Equity'!F63)+N('Changes in Equity'!F64)+N('Changes in Equity'!F66)+N('Changes in Equity'!F67)+N('Changes in Equity'!F68)-N('Changes in Equity'!F69),1) -> 0 | G53: =IF(AND(OR(B53="",B53=0),OR(C53="",C53=0),OR(D53="",D53=0),OR(E53="",E53=0),OR(F53="",F53=0)),"OK","CHECK") -> OK
A54: Other equity - General reserve: opening + movements = closing | B54: =ROUND(N('Changes in Equity'!G27)+N('Changes in Equity'!G28)+N('Changes in Equity'!G29)+N('Changes in Equity'!G31)+N('Changes in Equity'!G32)-N('Changes in Equity'!G33),1) -> 0 | C54: =ROUND(N('Changes in Equity'!G33)+N('Changes in Equity'!G35)+N('Changes in Equity'!G36)+N('Changes in Equity'!G38)+N('Changes in Equity'!G39)+N('Changes in Equity'!G40)+N('Changes in Equity'!G41)-N('Changes in Equity'!G42),1) -> 0 | D54: =ROUND(N('Changes in Equity'!G42)+N('Changes in Equity'!G44)+N('Changes in Equity'!G45)+N('Changes in Equity'!G47)+N('Changes in Equity'!G48)+N('Changes in Equity'!G49)-N('Changes in Equity'!G50),1) -> 0 | E54: =ROUND(N('Changes in Equity'!G50)+N('Changes in Equity'!G52)+N('Changes in Equity'!G53)+N('Changes in Equity'!G55)+N('Changes in Equity'!G56)+N('Changes in Equity'!G57)+N('Changes in Equity'!G58)+N('Changes in Equity'!G59)-N('Changes in Equity'!G60),1) -> 0 | F54: =ROUND(N('Changes in Equity'!G62)+N('Changes in Equity'!G63)+N('Changes in Equity'!G64)+N('Changes in Equity'!G66)+N('Changes in Equity'!G67)+N('Changes in Equity'!G68)-N('Changes in Equity'!G69),1) -> 0 | G54: =IF(AND(OR(B54="",B54=0),OR(C54="",C54=0),OR(D54="",D54=0),OR(E54="",E54=0),OR(F54="",F54=0)),"OK","CHECK") -> OK
A55: Other equity - Retained earnings: opening + movements = closing | B55: =ROUND(N('Changes in Equity'!H27)+N('Changes in Equity'!H28)+N('Changes in Equity'!H29)+N('Changes in Equity'!H31)+N('Changes in Equity'!H32)-N('Changes in Equity'!H33),1) -> 0 | C55: =ROUND(N('Changes in Equity'!H33)+N('Changes in Equity'!H35)+N('Changes in Equity'!H36)+N('Changes in Equity'!H38)+N('Changes in Equity'!H39)+N('Changes in Equity'!H40)+N('Changes in Equity'!H41)-N('Changes in Equity'!H42),1) -> 0 | D55: =ROUND(N('Changes in Equity'!H42)+N('Changes in Equity'!H44)+N('Changes in Equity'!H45)+N('Changes in Equity'!H47)+N('Changes in Equity'!H48)+N('Changes in Equity'!H49)-N('Changes in Equity'!H50),1) -> 0 | E55: =ROUND(N('Changes in Equity'!H50)+N('Changes in Equity'!H52)+N('Changes in Equity'!H53)+N('Changes in Equity'!H55)+N('Changes in Equity'!H56)+N('Changes in Equity'!H57)+N('Changes in Equity'!H58)+N('Changes in Equity'!H59)-N('Changes in Equity'!H60),1) -> 0 | F55: =ROUND(N('Changes in Equity'!H62)+N('Changes in Equity'!H63)+N('Changes in Equity'!H64)+N('Changes in Equity'!H66)+N('Changes in Equity'!H67)+N('Changes in Equity'!H68)-N('Changes in Equity'!H69),1) -> 0 | G55: =IF(AND(OR(B55="",B55=0),OR(C55="",C55=0),OR(D55="",D55=0),OR(E55="",E55=0),OR(F55="",F55=0)),"OK","CHECK") -> OK
A56: Other equity - Employee stock options reserve: opening + movements = closing | B56: =ROUND(N('Changes in Equity'!I27)+N('Changes in Equity'!I28)+N('Changes in Equity'!I29)+N('Changes in Equity'!I31)+N('Changes in Equity'!I32)-N('Changes in Equity'!I33),1) -> 0 | C56: =ROUND(N('Changes in Equity'!I33)+N('Changes in Equity'!I35)+N('Changes in Equity'!I36)+N('Changes in Equity'!I38)+N('Changes in Equity'!I39)+N('Changes in Equity'!I40)+N('Changes in Equity'!I41)-N('Changes in Equity'!I42),1) -> 0 | D56: =ROUND(N('Changes in Equity'!I42)+N('Changes in Equity'!I44)+N('Changes in Equity'!I45)+N('Changes in Equity'!I47)+N('Changes in Equity'!I48)+N('Changes in Equity'!I49)-N('Changes in Equity'!I50),1) -> 0 | E56: =ROUND(N('Changes in Equity'!I50)+N('Changes in Equity'!I52)+N('Changes in Equity'!I53)+N('Changes in Equity'!I55)+N('Changes in Equity'!I56)+N('Changes in Equity'!I57)+N('Changes in Equity'!I58)+N('Changes in Equity'!I59)-N('Changes in Equity'!I60),1) -> 0 | F56: =ROUND(N('Changes in Equity'!I62)+N('Changes in Equity'!I63)+N('Changes in Equity'!I64)+N('Changes in Equity'!I66)+N('Changes in Equity'!I67)+N('Changes in Equity'!I68)-N('Changes in Equity'!I69),1) -> 0 | G56: =IF(AND(OR(B56="",B56=0),OR(C56="",C56=0),OR(D56="",D56=0),OR(E56="",E56=0),OR(F56="",F56=0)),"OK","CHECK") -> OK
A57: Other equity - Convertible share warrants / Share application amount: opening + movements = closing | B57: =ROUND(N('Changes in Equity'!J27)+N('Changes in Equity'!J28)+N('Changes in Equity'!J29)+N('Changes in Equity'!J31)+N('Changes in Equity'!J32)-N('Changes in Equity'!J33),1) -> 0 | C57: =ROUND(N('Changes in Equity'!J33)+N('Changes in Equity'!J35)+N('Changes in Equity'!J36)+N('Changes in Equity'!J38)+N('Changes in Equity'!J39)+N('Changes in Equity'!J40)+N('Changes in Equity'!J41)-N('Changes in Equity'!J42),1) -> 0 | D57: =ROUND(N('Changes in Equity'!J42)+N('Changes in Equity'!J44)+N('Changes in Equity'!J45)+N('Changes in Equity'!J47)+N('Changes in Equity'!J48)+N('Changes in Equity'!J49)-N('Changes in Equity'!J50),1) -> 0 | E57: =ROUND(N('Changes in Equity'!J50)+N('Changes in Equity'!J52)+N('Changes in Equity'!J53)+N('Changes in Equity'!J55)+N('Changes in Equity'!J56)+N('Changes in Equity'!J57)+N('Changes in Equity'!J58)+N('Changes in Equity'!J59)-N('Changes in Equity'!J60),1) -> 0 | F57: =ROUND(N('Changes in Equity'!J62)+N('Changes in Equity'!J63)+N('Changes in Equity'!J64)+N('Changes in Equity'!J66)+N('Changes in Equity'!J67)+N('Changes in Equity'!J68)-N('Changes in Equity'!J69),1) -> 0 | G57: =IF(AND(OR(B57="",B57=0),OR(C57="",C57=0),OR(D57="",D57=0),OR(E57="",E57=0),OR(F57="",F57=0)),"OK","CHECK") -> OK
A58: Other equity - Total other equity: opening + movements = closing | B58: =ROUND(N('Changes in Equity'!K27)+N('Changes in Equity'!K28)+N('Changes in Equity'!K29)+N('Changes in Equity'!K31)+N('Changes in Equity'!K32)-N('Changes in Equity'!K33),1) -> 0 | C58: =ROUND(N('Changes in Equity'!K33)+N('Changes in Equity'!K35)+N('Changes in Equity'!K36)+N('Changes in Equity'!K38)+N('Changes in Equity'!K39)+N('Changes in Equity'!K40)+N('Changes in Equity'!K41)-N('Changes in Equity'!K42),1) -> 0 | D58: =ROUND(N('Changes in Equity'!K42)+N('Changes in Equity'!K44)+N('Changes in Equity'!K45)+N('Changes in Equity'!K47)+N('Changes in Equity'!K48)+N('Changes in Equity'!K49)-N('Changes in Equity'!K50),1) -> 0 | E58: =ROUND(N('Changes in Equity'!K50)+N('Changes in Equity'!K52)+N('Changes in Equity'!K53)+N('Changes in Equity'!K55)+N('Changes in Equity'!K56)+N('Changes in Equity'!K57)+N('Changes in Equity'!K58)+N('Changes in Equity'!K59)-N('Changes in Equity'!K60),1) -> 0 | F58: =ROUND(N('Changes in Equity'!K62)+N('Changes in Equity'!K63)+N('Changes in Equity'!K64)+N('Changes in Equity'!K66)+N('Changes in Equity'!K67)+N('Changes in Equity'!K68)-N('Changes in Equity'!K69),1) -> 0 | G58: =IF(AND(OR(B58="",B58=0),OR(C58="",C58=0),OR(D58="",D58=0),OR(E58="",E58=0),OR(F58="",F58=0)),"OK","CHECK") -> OK
A59: Other equity closing: the nine reserve columns add up to the Total column | B59: =ROUND(SUM('Changes in Equity'!B33:J33)-N('Changes in Equity'!K33),1) -> 0 | C59: =ROUND(SUM('Changes in Equity'!B42:J42)-N('Changes in Equity'!K42),1) -> 0 | D59: =ROUND(SUM('Changes in Equity'!B50:J50)-N('Changes in Equity'!K50),1) -> 0 | E59: =ROUND(SUM('Changes in Equity'!B60:J60)-N('Changes in Equity'!K60),1) -> 0 | F59: =ROUND(SUM('Changes in Equity'!B69:J69)-N('Changes in Equity'!K69),1) -> 0 | G59: =IF(AND(OR(B59="",B59=0),OR(C59="",C59=0),OR(D59="",D59=0),OR(E59="",E59=0),OR(F59="",F59=0)),"OK","CHECK") -> OK
A60: Financing liabilities table - roll-forwards
A61: Loans from banks and others: opening + movements = closing | B61: =ROUND(N('Financing Liabilities'!B7)+SUM('Financing Liabilities'!B9:B21)-N('Financing Liabilities'!B22),1) -> 0 | C61: =ROUND(N('Financing Liabilities'!B22)+SUM('Financing Liabilities'!B25:B39)-N('Financing Liabilities'!B40),1) -> 0 | D61: =ROUND(N('Financing Liabilities'!B40)+SUM('Financing Liabilities'!B43:B55)-N('Financing Liabilities'!B56),1) -> 0 | E61: =ROUND(N('Financing Liabilities'!B56)+SUM('Financing Liabilities'!B59:B73)-N('Financing Liabilities'!B74),1) -> 0 | F61: =ROUND(N('Financing Liabilities'!B76)+SUM('Financing Liabilities'!B78:B92)-N('Financing Liabilities'!B93),1) -> 0 | G61: =IF(AND(OR(B61="",B61=0),OR(C61="",C61=0),OR(D61="",D61=0),OR(E61="",E61=0),OR(F61="",F61=0)),"OK","CHECK") -> OK
A62: Deferred payment obligations: opening + movements = closing | B62: =ROUND(N('Financing Liabilities'!C7)+SUM('Financing Liabilities'!C9:C21)-N('Financing Liabilities'!C22),1) -> 0 | C62: =ROUND(N('Financing Liabilities'!C22)+SUM('Financing Liabilities'!C25:C39)-N('Financing Liabilities'!C40),1) -> 0 | D62: =ROUND(N('Financing Liabilities'!C40)+SUM('Financing Liabilities'!C43:C55)-N('Financing Liabilities'!C56),1) -> 0 | E62: =ROUND(N('Financing Liabilities'!C56)+SUM('Financing Liabilities'!C59:C73)-N('Financing Liabilities'!C74),1) -> 0 | F62: =ROUND(N('Financing Liabilities'!C76)+SUM('Financing Liabilities'!C78:C92)-N('Financing Liabilities'!C93),1) -> 0 | G62: =IF(AND(OR(B62="",B62=0),OR(C62="",C62=0),OR(D62="",D62=0),OR(E62="",E62=0),OR(F62="",F62=0)),"OK","CHECK") -> OK
A63: Derivative liabilities (net): opening + movements = closing | B63: =ROUND(N('Financing Liabilities'!D7)+SUM('Financing Liabilities'!D9:D21)-N('Financing Liabilities'!D22),1) -> 0 | C63: =ROUND(N('Financing Liabilities'!D22)+SUM('Financing Liabilities'!D25:D39)-N('Financing Liabilities'!D40),1) -> 0 | D63: =ROUND(N('Financing Liabilities'!D40)+SUM('Financing Liabilities'!D43:D55)-N('Financing Liabilities'!D56),1) -> 0 | E63: =ROUND(N('Financing Liabilities'!D56)+SUM('Financing Liabilities'!D59:D73)-N('Financing Liabilities'!D74),1) -> 0 | F63: =ROUND(N('Financing Liabilities'!D76)+SUM('Financing Liabilities'!D78:D92)-N('Financing Liabilities'!D93),1) -> 0 | G63: =IF(AND(OR(B63="",B63=0),OR(C63="",C63=0),OR(D63="",D63=0),OR(E63="",E63=0),OR(F63="",F63=0)),"OK","CHECK") -> OK
A64: Interest accrued but not due: opening + movements = closing | B64: =ROUND(N('Financing Liabilities'!E7)+SUM('Financing Liabilities'!E9:E21)-N('Financing Liabilities'!E22),1) -> 0 | C64: =ROUND(N('Financing Liabilities'!E22)+SUM('Financing Liabilities'!E25:E39)-N('Financing Liabilities'!E40),1) -> 0 | D64: =ROUND(N('Financing Liabilities'!E40)+SUM('Financing Liabilities'!E43:E55)-N('Financing Liabilities'!E56),1) -> 0 | E64: =ROUND(N('Financing Liabilities'!E56)+SUM('Financing Liabilities'!E59:E73)-N('Financing Liabilities'!E74),1) -> 0 | F64: =ROUND(N('Financing Liabilities'!E76)+SUM('Financing Liabilities'!E78:E92)-N('Financing Liabilities'!E93),1) -> 0 | G64: =IF(AND(OR(B64="",B64=0),OR(C64="",C64=0),OR(D64="",D64=0),OR(E64="",E64=0),OR(F64="",F64=0)),"OK","CHECK") -> OK
A65: Lease liabilities: opening + movements = closing | B65: =ROUND(N('Financing Liabilities'!F7)+SUM('Financing Liabilities'!F9:F21)-N('Financing Liabilities'!F22),1) -> 0 | C65: =ROUND(N('Financing Liabilities'!F22)+SUM('Financing Liabilities'!F25:F39)-N('Financing Liabilities'!F40),1) -> 0 | D65: =ROUND(N('Financing Liabilities'!F40)+SUM('Financing Liabilities'!F43:F55)-N('Financing Liabilities'!F56),1) -> 0 | E65: =ROUND(N('Financing Liabilities'!F56)+SUM('Financing Liabilities'!F59:F73)-N('Financing Liabilities'!F74),1) -> 0 | F65: =ROUND(N('Financing Liabilities'!F76)+SUM('Financing Liabilities'!F78:F92)-N('Financing Liabilities'!F93),1) -> 0 | G65: =IF(AND(OR(B65="",B65=0),OR(C65="",C65=0),OR(D65="",D65=0),OR(E65="",E65=0),OR(F65="",F65=0)),"OK","CHECK") -> OK
A67: Each check recomputes a total with a formula from the figures typed on the other sheets and compares it with the total printed in the report.
A68: Figures are used exactly as printed (already rounded by the Group), so a nil difference means the reported statements foot.
